Workbook

Sheet Terms 
A1: Settlement | B1: 40130 | D1: Cost | E1: 10183896
A2: Maturity | B2: 42687 | D2: Face Value | E2: 11120346
A3: Rate | B3: 0.13 | D3: Discount | E3: =E2-E1 -> 936450.23
A4: Price | B4: =+E1/E2*100 -> 91.578947
A5: Redemption | B5: 100
A6: Coupon Frequency | B6: 4
A7: Day Basis | B7: 0
A8: Yield | B8: =YIELD(B1,B2,B3,B4,B5,B6,B7) -> 0.14961419
A9: Effective | B9: =EFFECT(B3,B6) -> 0.13647593

Sheet XIRR 
A1: Date | B1: Cash Flow | C1: XIRR
A2: 40130 | B2: -10183896 | C2: =XIRR(B2:B30,A2:A30) -> 0.15812421
A3: 40222 | B3: 361411.26
A4: 40311 | B4: 361411.26
A5: 40403 | B5: 361411.26
A6: 40495 | B6: 361411.26
A7: 40587 | B7: 361411.26
A8: 40676 | B8: 361411.26
A9: 40768 | B9: 361411.26
A10: 40860 | B10: 361411.26
A11: 40952 | B11: 361411.26
A12: 41042 | B12: 361411.26
A13: 41134 | B13: 361411.26
A14: 41226 | B14: 361411.26
... A30: 42687 | B30: 11481758

Sheet Carry Value Proof 
A1: Day Basis = 30/360 | E1: 0.15821962 | J1: Day Basis = 30/360 | N1: 0.14961419
A2: Date | B2: Cash Flow | C2: Face Value | D2: Carry Value | E2: Effective Interest Rate | F2: Disc Amortization | J2: Date | K2: Cash Flow | L2: Face Value | M2: Carry Value | N2: Effective Interest Rate | O2: Disc Amortization
A3: 40130 | B3: -10183896 | C3: 11120346 | D3: 10183896 | E3: =+E1 -> 0.15821962 | J3: 40130 | K3: -10183896 | L3: 11120346 | M3: 10183896 | N3: =+N1 -> 0.14961419
A4: 40222 | B4: 361411.26 | D4: =+D3+F4 -> 10225308 | F4: =(0.25*$E$3*D3)-B4 -> 41411.778 | J4: 40222 | K4: 361411.26 | M4: =+M3+O4 -> 10203399 | O4: =(0.25*$N$3*M3)-K4 -> 19502.592
A5: 40311 | B5: 361411.26 | D5: =+D4+F5 -> 10268358 | F5: =(0.25*$E$3*D4)-B5 -> 43049.817 | J5: 40311 | K5: 361411.26 | M5: =+M4+O5 -> 10223631 | O5: =(0.25*$N$3*M4)-K5 -> 20232.059
A6: 40403 | B6: 361411.26 | D6: =+D5+F6 -> 10313110 | F6: =(0.25*$E$3*D5)-B6 -> 44752.648 | J6: 40403 | K6: 361411.26 | M6: =+M5+O6 -> 10244620 | O6: =(0.25*$N$3*M5)-K6 -> 20988.809
A7: 40495 | B7: 361411.26 | D7: =+D6+F7 -> 10359633 | F7: =(0.25*$E$3*D6)-B7 -> 46522.835 | J7: 40495 | K7: 361411.26 | M7: =+M6+O7 -> 10266394 | O7: =(0.25*$N$3*M6)-K7 -> 21773.865
A8: 40587 | B8: 361411.26 | D8: =+D7+F8 -> 10407996 | F8: =(0.25*$E$3*D7)-B8 -> 48363.041 | J8: 40587 | K8: 361411.26 | M8: =+M7+O8 -> 10288982 | O8: =(0.25*$N$3*M7)-K8 -> 22588.285
A9: 40676 | B9: 361411.26 | D9: =+D8+F9 -> 10458272 | F9: =(0.25*$E$3*D8)-B9 -> 50276.037 | J9: 40676 | K9: 361411.26 | M9: =+M8+O9 -> 10312415 | O9: =(0.25*$N$3*M8)-K9 -> 23433.167
A10: 40768 | B10: 361411.26 | D10: =+D9+F10 -> 10510537 | F10: =(0.25*$E$3*D9)-B10 -> 52264.701 | J10: 40768 | K10: 361411.26 | M10: =+M9+O10 -> 10336725 | O10: =(0.25*$N$3*M9)-K10 -> 24309.651
A11: 40860 | B11: 361411.26 | D11: =+D10+F11 -> 10564869 | F11: =(0.25*$E$3*D10)-B11 -> 54332.026 | J11: 40860 | K11: 361411.26 | M11: =+M10+O11 -> 10361944 | O11: =(0.25*$N$3*M10)-K11 -> 25218.918
A12: 40952 | B12: 361411.26 | D12: =+D11+F12 -> 10621350 | F12: =(0.25*$E$3*D11)-B12 -> 56481.124 | J12: 40952 | K12: 361411.26 | M12: =+M11+O12 -> 10388106 | O12: =(0.25*$N$3*M11)-K12 -> 26162.195
A13: 41042 | B13: 361411.26 | D13: =+D12+F13 -> 10680065 | F13: =(0.25*$E$3*D12)-B13 -> 58715.229 | J13: 41042 | K13: 361411.26 | M13: =+M12+O13 -> 10415246 | O13: =(0.25*$N$3*M12)-K13 -> 27140.754
A14: 41134 | B14: 361411.26 | D14: =+D13+F14 -> 10741103 | F14: =(0.25*$E$3*D13)-B14 -> 61037.705 | J14: 41134 | K14: 361411.26 | M14: =+M13+O14 -> 10443402 | O14: =(0.25*$N$3*M13)-K14 -> 28155.914
A15: 41226 | B15: 361411.26 | D15: =+D14+F15 -> 10804555 | F15: =(0.25*$E$3*D14)-B15 -> 63452.045 | J15: 41226 | K15: 361411.26 | M15: =+M14+O15 -> 10472611 | O15: =(0.25*$N$3*M14)-K15 -> 29209.045
... A19: 41591 | B19: 361411.26 | D19: =+D18+F19 -> 11084474 | F19: =(0.25*$E$3*D18)-B19 -> 74102.925 | J19: 41591 | K19: 361411.26 | M19: =+M18+O19 -> 10600789 | O19: =(0.25*$N$3*M18)-K19 -> 33830.489
A20: 41683 | B20: 361411.26 | D20: =+D19+F20 -> 11161508 | F20: =(0.25*$E$3*D19)-B20 -> 77034.059 | G20: Discount Fully Amortized | J20: 41683 | K20: 361411.26 | M20: =+M19+O20 -> 10635885 | O20: =(0.25*$N$3*M19)-K20 -> 35095.87
A21: 41772 | B21: 361411.26 | D21: =+D20+F21 -> 11241590 | F21: =(0.25*$E$3*D20)-B21 -> 80081.134 | J21: 41772 | K21: 361411.26 | M21: =+M20+O21 -> 10672294 | O21: =(0.25*$N$3*M20)-K21 -> 36408.58
A22: 41864 | B22: 361411.26 | D22: =+D21+F22 -> 11324838 | F22: =(0.25*$E$3*D21)-B22 -> 83248.735 | J22: 41864 | K22: 361411.26 | M22: =+M21+O22 -> 10710064 | O22: =(0.25*$N$3*M21)-K22 -> 37770.39
A23: 41956 | B23: 361411.26 | D23: =+D22+F23 -> 11411380 | F23: =(0.25*$E$3*D22)-B23 -> 86541.631 | J23: 41956 | K23: 361411.26 | M23: =+M22+O23 -> 10749247 | O23: =(0.25*$N$3*M22)-K23 -> 39183.136
A24: 42048 | B24: 361411.26 | D24: =+D23+F24 -> 11501345 | F24: =(0.25*$E$3*D23)-B24 -> 89964.777 | J24: 42048 | K24: 361411.26 | M24: =+M23+O24 -> 10789896 | O24: =(0.25*$N$3*M23)-K24 -> 40648.725
A25: 42137 | B25: 361411.26 | D25: =+D24+F25 -> 11594868 | F25: =(0.25*$E$3*D24)-B25 -> 93523.325 | J25: 42137 | K25: 361411.26 | M25: =+M24+O25 -> 10832065 | O25: =(0.25*$N$3*M24)-K25 -> 42169.131
A26: 42229 | B26: 361411.26 | D26: =+D25+F26 -> 11692091 | F26: =(0.25*$E$3*D25)-B26 -> 97222.631 | J26: 42229 | K26: 361411.26 | M26: =+M25+O26 -> 10875811 | O26: =(0.25*$N$3*M25)-K26 -> 43746.406
A27: 42321 | B27: 361411.26 | D27: =+D26+F27 -> 11793159 | F27: =(0.25*$E$3*D26)-B27 -> 101068.26 | J27: 42321 | K27: 361411.26 | M27: =+M26+O27 -> 10921194 | O27: =(0.25*$N$3*M26)-K27 -> 45382.677
A28: 42413 | B28: 361411.26 | D28: =+D27+F28 -> 11898225 | F28: =(0.25*$E$3*D27)-B28 -> 105066.01 | J28: 42413 | K28: 361411.26 | M28: =+M27+O28 -> 10968274 | O28: =(0.25*$N$3*M27)-K28 -> 47080.15
A29: 42503 | B29: 361411.26 | D29: =+D28+F29 -> 12007447 | F29: =(0.25*$E$3*D28)-B29 -> 109221.88 | J29: 42503 | K29: 361411.26 | M29: =+M28+O29 -> 11017115 | O29: =(0.25*$N$3*M28)-K29 -> 48841.115
A30: 42595 | B30: 361411.26 | D30: =+D29+F30 -> 12120989 | F30: =(0.25*$E$3*D29)-B30 -> 113542.15 | J30: 42595 | K30: 361411.26 | M30: =+M29+O30 -> 11067783 | O30: =(0.25*$N$3*M29)-K30 -> 50667.946
A31: 42687 | B31: 361411.26 | D31: =+D30+F31 -> 12239022 | F31: =(0.25*$E$3*D30)-B31 -> 118033.29 | J31: 42687 | K31: 361411.26 | M31: =+M30+O31 -> 11120346 | O31: =(0.25*$N$3*M30)-K31 -> 52563.107
F32: =SUM(F4:F31) -> 2055126 | O32: =SUM(O4:O31) -> 936450.23

Sheet Iteration 1
A1: Date | B1: Cash Flow | C1: Face Value | D1: Coupon Rate | E1: Cash Payment | F1: Discount Rate | G1: Disc Amortization | H1: Carry Value
A2: 40130 | B2: -10183896 | C2: 11120346 | D2: 0.13 | F2: 0 | H2: =+B2*-1 -> 10183896
A3: 40222 | B3: 361411.26 | C3: 11120346 | D3: 0.13 | E3: =+D3*C3*0.25 -> 361411.26 | F3: 0 | G3: =E3-((H2*0.25*F3)) -> 361411.26 | H3: =+H2-G3 -> 9822484.9
A4: 40311 | B4: 361411.26 | C4: 11120346 | D4: 0.13 | E4: =+D4*C4*0.25 -> 361411.26 | F4: 0 | G4: =E4-((H3*0.25*F4)) -> 361411.26 | H4: =+H3-G4 -> 9461073.7
A5: 40403 | B5: 361411.26 | C5: 11120346 | D5: 0.13 | E5: =+D5*C5*0.25 -> 361411.26 | F5: 0 | G5: =E5-((H4*0.25*F5)) -> 361411.26 | H5: =+H4-G5 -> 9099662.4
A6: 40495 | B6: 361411.26 | C6: 11120346 | D6: 0.13 | E6: =+D6*C6*0.25 -> 361411.26 | F6: 0 | G6: =E6-((H5*0.25*F6)) -> 361411.26 | H6: =+H5-G6 -> 8738251.2
A7: 40587 | B7: 361411.26 | C7: 11120346 | D7: 0.13 | E7: =+D7*C7*0.25 -> 361411.26 | F7: 0 | G7: =E7-((H6*0.25*F7)) -> 361411.26 | H7: =+H6-G7 -> 8376839.9
A8: 40676 | B8: 361411.26 | C8: 11120346 | D8: 0.13 | E8: =+D8*C8*0.25 -> 361411.26 | F8: 0 | G8: =E8-((H7*0.25*F8)) -> 361411.26 | H8: =+H7-G8 -> 8015428.6
A9: 40768 | B9: 361411.26 | C9: 11120346 | D9: 0.13 | E9: =+D9*C9*0.25 -> 361411.26 | F9: 0 | G9: =E9-((H8*0.25*F9)) -> 361411.26 | H9: =+H8-G9 -> 7654017.4
A10: 40860 | B10: 361411.26 | C10: 11120346 | D10: 0.13 | E10: =+D10*C10*0.25 -> 361411.26 | F10: 0 | G10: =E10-((H9*0.25*F10)) -> 361411.26 | H10: =+H9-G10 -> 7292606.1
A11: 40952 | B11: 361411.26 | C11: 11120346 | D11: 0.13 | E11: =+D11*C11*0.25 -> 361411.26 | F11: 0 | G11: =E11-((H10*0.25*F11)) -> 361411.26 | H11: =+H10-G11 -> 6931194.9
A12: 41042 | B12: 361411.26 | C12: 11120346 | D12: 0.13 | E12: =+D12*C12*0.25 -> 361411.26 | F12: 0 | G12: =E12-((H11*0.25*F12)) -> 361411.26 | H12: =+H11-G12 -> 6569783.6
A13: 41134 | B13: 361411.26 | C13: 11120346 | D13: 0.13 | E13: =+D13*C13*0.25 -> 361411.26 | F13: 0 | G13: =E13-((H12*0.25*F13)) -> 361411.26 | H13: =+H12-G13 -> 6208372.4
A14: 41226 | B14: 361411.26 | C14: 11120346 | D14: 0.13 | E14: =+D14*C14*0.25 -> 361411.26 | F14: 0 | G14: =E14-((H13*0.25*F14)) -> 361411.26 | H14: =+H13-G14 -> 5846961.1
... A29: 42595 | B29: 361411.26 | C29: 11120346 | D29: 0.13 | E29: =+D29*C29*0.25 -> 361411.26 | F29: 0 | G29: =E29-((H28*0.25*F29)) -> 361411.26 | H29: =+H28-G29 -> 425792.21
A30: 42687 | B30: =+B29 -> 361411.26 | C30: 11120346 | D30: 0.13 | E30: =+D30*C30*0.25 -> 361411.26 | F30: 0 | G30: =E30-((H29*0.25*F30)) -> 361411.26 | H30: =+H29-G30 -> 64380.949
F34: XIRR Function | G34: =H30-C2 -> -11055965
F36: Tolerance | G36: 0.01

Sheet Iteration 2
A1: Date | B1: Cash Flow | C1: Face Value | D1: Coupon Rate | E1: Cash Payment | F1: Discount Rate | G1: Disc Amortization | H1: Carry Value
A2: 40130 | B2: -10183896 | C2: 11120346 | D2: 0.13 | F2: 0.0125 | H2: =+B2*-1 -> 10183896
A3: 40222 | B3: 361411.26 | C3: 11120346 | D3: 0.13 | E3: =+D3*C3*0.25 -> 361411.26 | F3: 0.0125 | G3: =E3-((H2*0.25*F3)) -> 329586.58 | H3: =+H2-G3 -> 9854309.6
A4: 40311 | B4: 361411.26 | C4: 11120346 | D4: 0.13 | E4: =+D4*C4*0.25 -> 361411.26 | F4: 0.0125 | G4: =E4-((H3*0.25*F4)) -> 330616.54 | H4: =+H3-G4 -> 9523693.1
A5: 40403 | B5: 361411.26 | C5: 11120346 | D5: 0.13 | E5: =+D5*C5*0.25 -> 361411.26 | F5: 0.0125 | G5: =E5-((H4*0.25*F5)) -> 331649.72 | H5: =+H4-G5 -> 9192043.4
A6: 40495 | B6: 361411.26 | C6: 11120346 | D6: 0.13 | E6: =+D6*C6*0.25 -> 361411.26 | F6: 0.0125 | G6: =E6-((H5*0.25*F6)) -> 332686.12 | H6: =+H5-G6 -> 8859357.2
A7: 40587 | B7: 361411.26 | C7: 11120346 | D7: 0.13 | E7: =+D7*C7*0.25 -> 361411.26 | F7: 0.0125 | G7: =E7-((H6*0.25*F7)) -> 333725.77 | H7: =+H6-G7 -> 8525631.5
A8: 40676 | B8: 361411.26 | C8: 11120346 | D8: 0.13 | E8: =+D8*C8*0.25 -> 361411.26 | F8: 0.0125 | G8: =E8-((H7*0.25*F8)) -> 334768.66 | H8: =+H7-G8 -> 8190862.8
A9: 40768 | B9: 361411.26 | C9: 11120346 | D9: 0.13 | E9: =+D9*C9*0.25 -> 361411.26 | F9: 0.0125 | G9: =E9-((H8*0.25*F9)) -> 335814.81 | H9: =+H8-G9 -> 7855048
A10: 40860 | B10: 361411.26 | C10: 11120346 | D10: 0.13 | E10: =+D10*C10*0.25 -> 361411.26 | F10: 0.0125 | G10: =E10-((H9*0.25*F10)) -> 336864.23 | H10: =+H9-G10 -> 7518183.8
A11: 40952 | B11: 361411.26 | C11: 11120346 | D11: 0.13 | E11: =+D11*C11*0.25 -> 361411.26 | F11: 0.0125 | G11: =E11-((H10*0.25*F11)) -> 337916.93 | H11: =+H10-G11 -> 7180266.8
A12: 41042 | B12: 361411.26 | C12: 11120346 | D12: 0.13 | E12: =+D12*C12*0.25 -> 361411.26 | F12: 0.0125 | G12: =E12-((H11*0.25*F12)) -> 338972.93 | H12: =+H11-G12 -> 6841293.9
A13: 41134 | B13: 361411.26 | C13: 11120346 | D13: 0.13 | E13: =+D13*C13*0.25 -> 361411.26 | F13: 0.0125 | G13: =E13-((H12*0.25*F13)) -> 340032.22 | H13: =+H12-G13 -> 6501261.7
A14: 41226 | B14: 361411.26 | C14: 11120346 | D14: 0.13 | E14: =+D14*C14*0.25 -> 361411.26 | F14: 0.0125 | G14: =E14-((H13*0.25*F14)) -> 341094.82 | H14: =+H13-G14 -> 6160166.9
... A29: 42595 | B29: 361411.26 | C29: 11120346 | D29: 0.13 | E29: =+D29*C29*0.25 -> 361411.26 | F29: 0.0125 | G29: =E29-((H28*0.25*F29)) -> 357438.17 | H29: =+H28-G29 -> 913949.62
A30: 42687 | B30: =+B29 -> 361411.26 | C30: 11120346 | D30: 0.13 | E30: =+D30*C30*0.25 -> 361411.26 | F30: 0.0125 | G30: =E30-((H29*0.25*F30)) -> 358555.17 | H30: =+H29-G30 -> 555394.45
F34: XIRR Function | G34: =H30-C2 -> -10564952
F36: Tolerance | G36: 0.01

Sheet Iteration 3
A1: Date | B1: Cash Flow | C1: Face Value | D1: Coupon Rate | E1: Cash Payment | F1: Discount Rate | G1: Disc Amortization | H1: Carry Value
A2: 40130 | B2: -10183896 | C2: 11120346 | D2: 0.13 | F2: 0.0875 | H2: =+B2*-1 -> 10183896
A3: 40222 | B3: 361411.26 | C3: 11120346 | D3: 0.13 | E3: =+D3*C3*0.25 -> 361411.26 | F3: 0.0875 | G3: =E3-((H2*0.25*F3)) -> 138638.53 | H3: =+H2-G3 -> 10045258
A4: 40311 | B4: 361411.26 | C4: 11120346 | D4: 0.13 | E4: =+D4*C4*0.25 -> 361411.26 | F4: 0.0875 | G4: =E4-((H3*0.25*F4)) -> 141671.25 | H4: =+H3-G4 -> 9903586.4
A5: 40403 | B5: 361411.26 | C5: 11120346 | D5: 0.13 | E5: =+D5*C5*0.25 -> 361411.26 | F5: 0.0875 | G5: =E5-((H4*0.25*F5)) -> 144770.31 | H5: =+H4-G5 -> 9758816.1
A6: 40495 | B6: 361411.26 | C6: 11120346 | D6: 0.13 | E6: =+D6*C6*0.25 -> 361411.26 | F6: 0.0875 | G6: =E6-((H5*0.25*F6)) -> 147937.16 | H6: =+H5-G6 -> 9610879
A7: 40587 | B7: 361411.26 | C7: 11120346 | D7: 0.13 | E7: =+D7*C7*0.25 -> 361411.26 | F7: 0.0875 | G7: =E7-((H6*0.25*F7)) -> 151173.28 | H7: =+H6-G7 -> 9459705.7
A8: 40676 | B8: 361411.26 | C8: 11120346 | D8: 0.13 | E8: =+D8*C8*0.25 -> 361411.26 | F8: 0.0875 | G8: =E8-((H7*0.25*F8)) -> 154480.2 | H8: =+H7-G8 -> 9305225.5
A9: 40768 | B9: 361411.26 | C9: 11120346 | D9: 0.13 | E9: =+D9*C9*0.25 -> 361411.26 | F9: 0.0875 | G9: =E9-((H8*0.25*F9)) -> 157859.45 | H9: =+H8-G9 -> 9147366
A10: 40860 | B10: 361411.26 | C10: 11120346 | D10: 0.13 | E10: =+D10*C10*0.25 -> 361411.26 | F10: 0.0875 | G10: =E10-((H9*0.25*F10)) -> 161312.63 | H10: =+H9-G10 -> 8986053.4
A11: 40952 | B11: 361411.26 | C11: 11120346 | D11: 0.13 | E11: =+D11*C11*0.25 -> 361411.26 | F11: 0.0875 | G11: =E11-((H10*0.25*F11)) -> 164841.34 | H11: =+H10-G11 -> 8821212.1
A12: 41042 | B12: 361411.26 | C12: 11120346 | D12: 0.13 | E12: =+D12*C12*0.25 -> 361411.26 | F12: 0.0875 | G12: =E12-((H11*0.25*F12)) -> 168447.25 | H12: =+H11-G12 -> 8652764.8
A13: 41134 | B13: 361411.26 | C13: 11120346 | D13: 0.13 | E13: =+D13*C13*0.25 -> 361411.26 | F13: 0.0875 | G13: =E13-((H12*0.25*F13)) -> 172132.03 | H13: =+H12-G13 -> 8480632.8
A14: 41226 | B14: 361411.26 | C14: 11120346 | D14: 0.13 | E14: =+D14*C14*0.25 -> 361411.26 | F14: 0.0875 | G14: =E14-((H13*0.25*F14)) -> 175897.42 | H14: =+H13-G14 -> 8304735.4
... A29: 42595 | B29: 361411.26 | C29: 11120346 | D29: 0.13 | E29: =+D29*C29*0.25 -> 361411.26 | F29: 0.0875 | G29: =E29-((H28*0.25*F29)) -> 243347.04 | H29: =+H28-G29 -> 5153874.2
A30: 42687 | B30: =+B29 -> 361411.26 | C30: 11120346 | D30: 0.13 | E30: =+D30*C30*0.25 -> 361411.26 | F30: 0.0875 | G30: =E30-((H29*0.25*F30)) -> 248670.26 | H30: =+H29-G30 -> 4905203.9
F34: XIRR Function | G34: =H30-C2 -> -6215142.5
F36: Tolerance | G36: 0.01

Sheet Get Rate for Iteration 4
A1: A3 = A2-y2*(a2-a1)/y2-y1
A4: A3 | B4: =B5-B7*(B5-B6)/(B7-B8) -> 0.19466232 | C4: New Rate
A5: a2 | B5: 0.0875 | C5: Rate from Iteration 2
A6: a1 | B6: 0.0125 | C6: Rate from Iteration 1
A7: y2 | B7: ='Iteration 3'!G34 -> -6215142.5 | C7: Result from Iteration 2
A8: y1 | B8: ='Iteration 2'!G34 -> -10564952 | C8: Result from Iteration1

Sheet Iteration 4 
A1: Date | B1: Cash Flow | C1: Face Value | D1: Coupon Rate | E1: Cash Payment | F1: Discount Rate | G1: Disc Amortization | H1: Carry Value
A2: 40130 | B2: -10183896 | C2: 11120346 | D2: 0.13 | F2: ='Get Rate for Iteration 4'!$B$4 -> 0.19466232 | H2: =+B2*-1 -> 10183896
A3: 40222 | B3: 361411.26 | C3: 11120346 | D3: 0.13 | E3: =+D3*C3*0.25 -> 361411.26 | F3: ='Get Rate for Iteration 4'!$B$4 -> 0.19466232 | G3: =E3-((H2*0.25*F3)) -> -134193.96 | H3: =+H2-G3 -> 10318090
A4: 40311 | B4: 361411.26 | C4: 11120346 | D4: 0.13 | E4: =+D4*C4*0.25 -> 361411.26 | F4: ='Get Rate for Iteration 4'!$B$4 -> 0.19466232 | G4: =E4-((H3*0.25*F4)) -> -140724.59 | H4: =+H3-G4 -> 10458815
A5: 40403 | B5: 361411.26 | C5: 11120346 | D5: 0.13 | E5: =+D5*C5*0.25 -> 361411.26 | F5: ='Get Rate for Iteration 4'!$B$4 -> 0.19466232 | G5: =E5-((H4*0.25*F5)) -> -147573.04 | H5: =+H4-G5 -> 10606388
A6: 40495 | B6: 361411.26 | C6: 11120346 | D6: 0.13 | E6: =+D6*C6*0.25 -> 361411.26 | F6: ='Get Rate for Iteration 4'!$B$4 -> 0.19466232 | G6: =E6-((H5*0.25*F6)) -> -154754.76 | H6: =+H5-G6 -> 10761143
A7: 40587 | B7: 361411.26 | C7: 11120346 | D7: 0.13 | E7: =+D7*C7*0.25 -> 361411.26 | F7: ='Get Rate for Iteration 4'!$B$4 -> 0.19466232 | G7: =E7-((H6*0.25*F7)) -> -162285.99 | H7: =+H6-G7 -> 10923429
A8: 40676 | B8: 361411.26 | C8: 11120346 | D8: 0.13 | E8: =+D8*C8*0.25 -> 361411.26 | F8: ='Get Rate for Iteration 4'!$B$4 -> 0.19466232 | G8: =E8-((H7*0.25*F8)) -> -170183.74 | H8: =+H7-G8 -> 11093612
A9: 40768 | B9: 361411.26 | C9: 11120346 | D9: 0.13 | E9: =+D9*C9*0.25 -> 361411.26 | F9: ='Get Rate for Iteration 4'!$B$4 -> 0.19466232 | G9: =E9-((H8*0.25*F9)) -> -178465.83 | H9: =+H8-G9 -> 11272078
A10: 40860 | B10: 361411.26 | C10: 11120346 | D10: 0.13 | E10: =+D10*C10*0.25 -> 361411.26 | F10: ='Get Rate for Iteration 4'!$B$4 -> 0.19466232 | G10: =E10-((H9*0.25*F10)) -> -187150.97 | H10: =+H9-G10 -> 11459229
A11: 40952 | B11: 361411.26 | C11: 11120346 | D11: 0.13 | E11: =+D11*C11*0.25 -> 361411.26 | F11: ='Get Rate for Iteration 4'!$B$4 -> 0.19466232 | G11: =E11-((H10*0.25*F11)) -> -196258.78 | H11: =+H10-G11 -> 11655488
A12: 41042 | B12: 361411.26 | C12: 11120346 | D12: 0.13 | E12: =+D12*C12*0.25 -> 361411.26 | F12: ='Get Rate for Iteration 4'!$B$4 -> 0.19466232 | G12: =E12-((H11*0.25*F12)) -> -205809.83 | H12: =+H11-G12 -> 11861298
A13: 41134 | B13: 361411.26 | C13: 11120346 | D13: 0.13 | E13: =+D13*C13*0.25 -> 361411.26 | F13: ='Get Rate for Iteration 4'!$B$4 -> 0.19466232 | G13: =E13-((H12*0.25*F13)) -> -215825.68 | H13: =+H12-G13 -> 12077123
A14: 41226 | B14: 361411.26 | C14: 11120346 | D14: 0.13 | E14: =+D14*C14*0.25 -> 361411.26 | F14: ='Get Rate for Iteration 4'!$B$4 -> 0.19466232 | G14: =E14-((H13*0.25*F14)) -> -226328.97 | H14: =+H13-G14 -> 12303452
... A29: 42595 | B29: 361411.26 | C29: 11120346 | D29: 0.13 | E29: =+D29*C29*0.25 -> 361411.26 | F29: ='Get Rate for Iteration 4'!$B$4 -> 0.19466232 | G29: =E29-((H28*0.25*F29)) -> -461631.4 | H29: =+H28-G29 -> 17373844
A30: 42687 | B30: =+B29 -> 361411.26 | C30: 11120346 | D30: 0.13 | E30: =+D30*C30*0.25 -> 361411.26 | F30: ='Get Rate for Iteration 4'!$B$4 -> 0.19466232 | G30: =E30-((H29*0.25*F30)) -> -484096.96 | H30: =+H29-G30 -> 17857941
F34: XIRR Function | G34: =H30-C2 -> 6737594.8
F36: Tolerance | G36: 0.01

Sheet Get Rate for Iteration 5
A1: A3 = A2-y2*(a2-a1)/y2-y1
A4: A3 | B4: =B5-B7*(B5-B6)/(B7-B8) -> 0.13891995 | C4: New Rate
A5: a2 | B5: ='Iteration 4 '!F2 -> 0.19466232 | C5: Rate from Iteration 2
A6: a1 | B6: ='Iteration 3'!F2 -> 0.0875 | C6: Rate from Iteration 1
A7: y2 | B7: ='Iteration 4 '!G34 -> 6737594.8 | C7: Result from Iteration 2
A8: y1 | B8: ='Iteration 3'!G34 -> -6215142.5 | C8: Result from Iteration1

Sheet Iteration 5
A1: Date | B1: Cash Flow | C1: Face Value | D1: Coupon Rate | E1: Cash Payment | F1: Discount Rate | G1: Disc Amortization | H1: Carry Value
A2: 40130 | B2: -10183896 | C2: 11120346 | D2: 0.13 | F2: ='Get Rate for Iteration 5'!$B$4 -> 0.13891995 | H2: =+B2*-1 -> 10183896
A3: 40222 | B3: 361411.26 | C3: 11120346 | D3: 0.13 | E3: =+D3*C3*0.25 -> 361411.26 | F3: ='Get Rate for Iteration 5'!$B$4 -> 0.13891995 | G3: =E3-((H2*0.25*F3)) -> 7724.6701 | H3: =+H2-G3 -> 10176172
A4: 40311 | B4: 361411.26 | C4: 11120346 | D4: 0.13 | E4: =+D4*C4*0.25 -> 361411.26 | F4: ='Get Rate for Iteration 5'!$B$4 -> 0.13891995 | G4: =E4-((H3*0.25*F4)) -> 7992.9478 | H4: =+H3-G4 -> 10168179
A5: 40403 | B5: 361411.26 | C5: 11120346 | D5: 0.13 | E5: =+D5*C5*0.25 -> 361411.26 | F5: ='Get Rate for Iteration 5'!$B$4 -> 0.13891995 | G5: =E5-((H4*0.25*F5)) -> 8270.5428 | H5: =+H4-G5 -> 10159908
A6: 40495 | B6: 361411.26 | C6: 11120346 | D6: 0.13 | E6: =+D6*C6*0.25 -> 361411.26 | F6: ='Get Rate for Iteration 5'!$B$4 -> 0.13891995 | G6: =E6-((H5*0.25*F6)) -> 8557.7786 | H6: =+H5-G6 -> 10151350
A7: 40587 | B7: 361411.26 | C7: 11120346 | D7: 0.13 | E7: =+D7*C7*0.25 -> 361411.26 | F7: ='Get Rate for Iteration 5'!$B$4 -> 0.13891995 | G7: =E7-((H6*0.25*F7)) -> 8854.9902 | H7: =+H6-G7 -> 10142495
A8: 40676 | B8: 361411.26 | C8: 11120346 | D8: 0.13 | E8: =+D8*C8*0.25 -> 361411.26 | F8: ='Get Rate for Iteration 5'!$B$4 -> 0.13891995 | G8: =E8-((H7*0.25*F8)) -> 9162.5239 | H8: =+H7-G8 -> 10133333
A9: 40768 | B9: 361411.26 | C9: 11120346 | D9: 0.13 | E9: =+D9*C9*0.25 -> 361411.26 | F9: ='Get Rate for Iteration 5'!$B$4 -> 0.13891995 | G9: =E9-((H8*0.25*F9)) -> 9480.7382 | H9: =+H8-G9 -> 10123852
A10: 40860 | B10: 361411.26 | C10: 11120346 | D10: 0.13 | E10: =+D10*C10*0.25 -> 361411.26 | F10: ='Get Rate for Iteration 5'!$B$4 -> 0.13891995 | G10: =E10-((H9*0.25*F10)) -> 9810.0041 | H10: =+H9-G10 -> 10114042
A11: 40952 | B11: 361411.26 | C11: 11120346 | D11: 0.13 | E11: =+D11*C11*0.25 -> 361411.26 | F11: ='Get Rate for Iteration 5'!$B$4 -> 0.13891995 | G11: =E11-((H10*0.25*F11)) -> 10150.705 | H11: =+H10-G11 -> 10103891
A12: 41042 | B12: 361411.26 | C12: 11120346 | D12: 0.13 | E12: =+D12*C12*0.25 -> 361411.26 | F12: ='Get Rate for Iteration 5'!$B$4 -> 0.13891995 | G12: =E12-((H11*0.25*F12)) -> 10503.239 | H12: =+H11-G12 -> 10093388
A13: 41134 | B13: 361411.26 | C13: 11120346 | D13: 0.13 | E13: =+D13*C13*0.25 -> 361411.26 | F13: ='Get Rate for Iteration 5'!$B$4 -> 0.13891995 | G13: =E13-((H12*0.25*F13)) -> 10868.017 | H13: =+H12-G13 -> 10082520
A14: 41226 | B14: 361411.26 | C14: 11120346 | D14: 0.13 | E14: =+D14*C14*0.25 -> 361411.26 | F14: ='Get Rate for Iteration 5'!$B$4 -> 0.13891995 | G14: =E14-((H13*0.25*F14)) -> 11245.463 | H14: =+H13-G14 -> 10071275
... A29: 42595 | B29: 361411.26 | C29: 11120346 | D29: 0.13 | E29: =+D29*C29*0.25 -> 361411.26 | F29: ='Get Rate for Iteration 5'!$B$4 -> 0.13891995 | G29: =E29-((H28*0.25*F29)) -> 18766.482 | H29: =+H28-G29 -> 9847196.6
A30: 42687 | B30: =+B29 -> 361411.26 | C30: 11120346 | D30: 0.13 | E30: =+D30*C30*0.25 -> 361411.26 | F30: ='Get Rate for Iteration 5'!$B$4 -> 0.13891995 | G30: =E30-((H29*0.25*F30)) -> 19418.242 | H30: =+H29-G30 -> 9827778.4
F34: XIRR Function | G34: =H30-C2 -> -1292568
F36: Tolerance | G36: 0.01

Sheet Get Rate for Iteration 6
A1: A3 = A2-y2*(a2-a1)/y2-y1
A4: A3 | B4: =B5-B7*(B5-B6)/(B7-B8) -> 0.14789247 | C4: New Rate
A5: a2 | B5: ='Iteration 5'!F2 -> 0.13891995 | C5: Rate from Iteration 2
A6: a1 | B6: ='Iteration 4 '!F2 -> 0.19466232 | C6: Rate from Iteration 1
A7: y2 | B7: ='Iteration 5'!G34 -> -1292568 | C7: Result from Iteration 2
A8: y1 | B8: ='Iteration 4 '!G34 -> 6737594.8 | C8: Result from Iteration1

Sheet Iteration 6
A1: Date | B1: Cash Flow | C1: Face Value | D1: Coupon Rate | E1: Cash Payment | F1: Discount Rate | G1: Disc Amortization | H1: Carry Value
A2: 40130 | B2: -10183896 | C2: 11120346 | D2: 0.13 | F2: ='Get Rate for Iteration 6'!$B$4 -> 0.14789247 | H2: =+B2*-1 -> 10183896
A3: 40222 | B3: 361411.26 | C3: 11120346 | D3: 0.13 | E3: =+D3*C3*0.25 -> 361411.26 | F3: ='Get Rate for Iteration 6'!$B$4 -> 0.14789247 | G3: =E3-((H2*0.25*F3)) -> -15119.137 | H3: =+H2-G3 -> 10199015
A4: 40311 | B4: 361411.26 | C4: 11120346 | D4: 0.13 | E4: =+D4*C4*0.25 -> 361411.26 | F4: ='Get Rate for Iteration 6'!$B$4 -> 0.14789247 | G4: =E4-((H3*0.25*F4)) -> -15678.139 | H4: =+H3-G4 -> 10214693
A5: 40403 | B5: 361411.26 | C5: 11120346 | D5: 0.13 | E5: =+D5*C5*0.25 -> 361411.26 | F5: ='Get Rate for Iteration 6'!$B$4 -> 0.14789247 | G5: =E5-((H4*0.25*F5)) -> -16257.808 | H5: =+H4-G5 -> 10230951
A6: 40495 | B6: 361411.26 | C6: 11120346 | D6: 0.13 | E6: =+D6*C6*0.25 -> 361411.26 | F6: ='Get Rate for Iteration 6'!$B$4 -> 0.14789247 | G6: =E6-((H5*0.25*F6)) -> -16858.91 | H6: =+H5-G6 -> 10247810
A7: 40587 | B7: 361411.26 | C7: 11120346 | D7: 0.13 | E7: =+D7*C7*0.25 -> 361411.26 | F7: ='Get Rate for Iteration 6'!$B$4 -> 0.14789247 | G7: =E7-((H6*0.25*F7)) -> -17482.237 | H7: =+H6-G7 -> 10265292
A8: 40676 | B8: 361411.26 | C8: 11120346 | D8: 0.13 | E8: =+D8*C8*0.25 -> 361411.26 | F8: ='Get Rate for Iteration 6'!$B$4 -> 0.14789247 | G8: =E8-((H7*0.25*F8)) -> -18128.609 | H8: =+H7-G8 -> 10283421
A9: 40768 | B9: 361411.26 | C9: 11120346 | D9: 0.13 | E9: =+D9*C9*0.25 -> 361411.26 | F9: ='Get Rate for Iteration 6'!$B$4 -> 0.14789247 | G9: =E9-((H8*0.25*F9)) -> -18798.881 | H9: =+H8-G9 -> 10302220
A10: 40860 | B10: 361411.26 | C10: 11120346 | D10: 0.13 | E10: =+D10*C10*0.25 -> 361411.26 | F10: ='Get Rate for Iteration 6'!$B$4 -> 0.14789247 | G10: =E10-((H9*0.25*F10)) -> -19493.934 | H10: =+H9-G10 -> 10321714
A11: 40952 | B11: 361411.26 | C11: 11120346 | D11: 0.13 | E11: =+D11*C11*0.25 -> 361411.26 | F11: ='Get Rate for Iteration 6'!$B$4 -> 0.14789247 | G11: =E11-((H10*0.25*F11)) -> -20214.685 | H11: =+H10-G11 -> 10341929
A12: 41042 | B12: 361411.26 | C12: 11120346 | D12: 0.13 | E12: =+D12*C12*0.25 -> 361411.26 | F12: ='Get Rate for Iteration 6'!$B$4 -> 0.14789247 | G12: =E12-((H11*0.25*F12)) -> -20962.085 | H12: =+H11-G12 -> 10362891
A13: 41134 | B13: 361411.26 | C13: 11120346 | D13: 0.13 | E13: =+D13*C13*0.25 -> 361411.26 | F13: ='Get Rate for Iteration 6'!$B$4 -> 0.14789247 | G13: =E13-((H12*0.25*F13)) -> -21737.119 | H13: =+H12-G13 -> 10384628
A14: 41226 | B14: 361411.26 | C14: 11120346 | D14: 0.13 | E14: =+D14*C14*0.25 -> 361411.26 | F14: ='Get Rate for Iteration 6'!$B$4 -> 0.14789247 | G14: =E14-((H13*0.25*F14)) -> -22540.808 | H14: =+H13-G14 -> 10407169
... A29: 42595 | B29: 361411.26 | C29: 11120346 | D29: 0.13 | E29: =+D29*C29*0.25 -> 361411.26 | F29: ='Get Rate for Iteration 6'!$B$4 -> 0.14789247 | G29: =E29-((H28*0.25*F29)) -> -38858.135 | H29: =+H28-G29 -> 10864815
A30: 42687 | B30: =+B29 -> 361411.26 | C30: 11120346 | D30: 0.13 | E30: =+D30*C30*0.25 -> 361411.26 | F30: ='Get Rate for Iteration 6'!$B$4 -> 0.14789247 | G30: =E30-((H29*0.25*F30)) -> -40294.841 | H30: =+H29-G30 -> 10905110
F34: XIRR Function | G34: =H30-C2 -> -215236.23
F36: Tolerance | G36: 0.01

Sheet Get Rate for Iteration 7 
A1: A3 = A2-y2*(a2-a1)/y2-y1
A4: A3 | B4: =B5-B7*(B5-B6)/(B7-B8) -> 0.14968506 | C4: New Rate
A5: a2 | B5: ='Iteration 6'!F2 -> 0.14789247 | C5: Rate from Iteration 2
A6: a1 | B6: ='Iteration 5'!F2 -> 0.13891995 | C6: Rate from Iteration 1
A7: y2 | B7: ='Iteration 6'!G34 -> -215236.23 | C7: Result from Iteration 2
A8: y1 | B8: ='Iteration 5'!G34 -> -1292568 | C8: Result from Iteration1

Sheet Iteration 7 
A1: Date | B1: Cash Flow | C1: Face Value | D1: Coupon Rate | E1: Cash Payment | F1: Discount Rate | G1: Disc Amortization | H1: Carry Value
A2: 40130 | B2: -10183896 | C2: 11120346 | D2: 0.13 | F2: ='Get Rate for Iteration 7 '!$B$4 -> 0.14968506 | H2: =+B2*-1 -> 10183896
A3: 40222 | B3: 361411.26 | C3: 11120346 | D3: 0.13 | E3: =+D3*C3*0.25 -> 361411.26 | F3: ='Get Rate for Iteration 7 '!$B$4 -> 0.14968506 | G3: =E3-((H2*0.25*F3)) -> -19683.019 | H3: =+H2-G3 -> 10203579
A4: 40311 | B4: 361411.26 | C4: 11120346 | D4: 0.13 | E4: =+D4*C4*0.25 -> 361411.26 | F4: ='Get Rate for Iteration 7 '!$B$4 -> 0.14968506 | G4: =E4-((H3*0.25*F4)) -> -20419.582 | H4: =+H3-G4 -> 10223999
A5: 40403 | B5: 361411.26 | C5: 11120346 | D5: 0.13 | E5: =+D5*C5*0.25 -> 361411.26 | F5: ='Get Rate for Iteration 7 '!$B$4 -> 0.14968506 | G5: =E5-((H4*0.25*F5)) -> -21183.709 | H5: =+H4-G5 -> 10245183
A6: 40495 | B6: 361411.26 | C6: 11120346 | D6: 0.13 | E6: =+D6*C6*0.25 -> 361411.26 | F6: ='Get Rate for Iteration 7 '!$B$4 -> 0.14968506 | G6: =E6-((H5*0.25*F6)) -> -21976.43 | H6: =+H5-G6 -> 10267159
A7: 40587 | B7: 361411.26 | C7: 11120346 | D7: 0.13 | E7: =+D7*C7*0.25 -> 361411.26 | F7: ='Get Rate for Iteration 7 '!$B$4 -> 0.14968506 | G7: =E7-((H6*0.25*F7)) -> -22798.816 | H7: =+H6-G7 -> 10289958
A8: 40676 | B8: 361411.26 | C8: 11120346 | D8: 0.13 | E8: =+D8*C8*0.25 -> 361411.26 | F8: ='Get Rate for Iteration 7 '!$B$4 -> 0.14968506 | G8: =E8-((H7*0.25*F8)) -> -23651.976 | H8: =+H7-G8 -> 10313610
A9: 40768 | B9: 361411.26 | C9: 11120346 | D9: 0.13 | E9: =+D9*C9*0.25 -> 361411.26 | F9: ='Get Rate for Iteration 7 '!$B$4 -> 0.14968506 | G9: =E9-((H8*0.25*F9)) -> -24537.063 | H9: =+H8-G9 -> 10338147
A10: 40860 | B10: 361411.26 | C10: 11120346 | D10: 0.13 | E10: =+D10*C10*0.25 -> 361411.26 | F10: ='Get Rate for Iteration 7 '!$B$4 -> 0.14968506 | G10: =E10-((H9*0.25*F10)) -> -25455.271 | H10: =+H9-G10 -> 10363602
A11: 40952 | B11: 361411.26 | C11: 11120346 | D11: 0.13 | E11: =+D11*C11*0.25 -> 361411.26 | F11: ='Get Rate for Iteration 7 '!$B$4 -> 0.14968506 | G11: =E11-((H10*0.25*F11)) -> -26407.84 | H11: =+H10-G11 -> 10390010
A12: 41042 | B12: 361411.26 | C12: 11120346 | D12: 0.13 | E12: =+D12*C12*0.25 -> 361411.26 | F12: ='Get Rate for Iteration 7 '!$B$4 -> 0.14968506 | G12: =E12-((H11*0.25*F12)) -> -27396.054 | H12: =+H11-G12 -> 10417406
A13: 41134 | B13: 361411.26 | C13: 11120346 | D13: 0.13 | E13: =+D13*C13*0.25 -> 361411.26 | F13: ='Get Rate for Iteration 7 '!$B$4 -> 0.14968506 | G13: =E13-((H12*0.25*F13)) -> -28421.249 | H13: =+H12-G13 -> 10445827
A14: 41226 | B14: 361411.26 | C14: 11120346 | D14: 0.13 | E14: =+D14*C14*0.25 -> 361411.26 | F14: ='Get Rate for Iteration 7 '!$B$4 -> 0.14968506 | G14: =E14-((H13*0.25*F14)) -> -29484.808 | H14: =+H13-G14 -> 10475312
... A29: 42595 | B29: 361411.26 | C29: 11120346 | D29: 0.13 | E29: =+D29*C29*0.25 -> 361411.26 | F29: ='Get Rate for Iteration 7 '!$B$4 -> 0.14968506 | G29: =E29-((H28*0.25*F29)) -> -51159.407 | H29: =+H28-G29 -> 11076192
A30: 42687 | B30: =+B29 -> 361411.26 | C30: 11120346 | D30: 0.13 | E30: =+D30*C30*0.25 -> 361411.26 | F30: ='Get Rate for Iteration 7 '!$B$4 -> 0.14968506 | G30: =E30-((H29*0.25*F30)) -> -53073.856 | H30: =+H29-G30 -> 11129266
F34: XIRR Function | G34: =H30-C2 -> 8919.4259
F36: Tolerance | G36: 0.01

Sheet Get Rate for Iteration 8 
A1: A3 = A2-y2*(a2-a1)/y2-y1
A4: A3 | B4: =B5-B7*(B5-B6)/(B7-B8) -> 0.14961373 | C4: New Rate
A5: a2 | B5: ='Iteration 7 '!F2 -> 0.14968506 | C5: Rate from Iteration 2
A6: a1 | B6: ='Iteration 6'!F2 -> 0.14789247 | C6: Rate from Iteration 1
A7: y2 | B7: ='Iteration 7 '!G34 -> 8919.4259 | C7: Result from Iteration 2
A8: y1 | B8: ='Iteration 6'!G34 -> -215236.23 | C8: Result from Iteration1

Sheet Iteration 8 
A1: Date | B1: Cash Flow | C1: Face Value | D1: Coupon Rate | E1: Cash Payment | F1: Discount Rate | G1: Disc Amortization | H1: Carry Value
A2: 40130 | B2: -10183896 | C2: 11120346 | D2: 0.13 | F2: ='Get Rate for Iteration 8 '!$B$4 -> 0.14961373 | H2: =+B2*-1 -> 10183896
A3: 40222 | B3: 361411.26 | C3: 11120346 | D3: 0.13 | E3: =+D3*C3*0.25 -> 361411.26 | F3: ='Get Rate for Iteration 8 '!$B$4 -> 0.14961373 | G3: =E3-((H2*0.25*F3)) -> -19501.416 | H3: =+H2-G3 -> 10203398
A4: 40311 | B4: 361411.26 | C4: 11120346 | D4: 0.13 | E4: =+D4*C4*0.25 -> 361411.26 | F4: ='Get Rate for Iteration 8 '!$B$4 -> 0.14961373 | G4: =E4-((H3*0.25*F4)) -> -20230.836 | H4: =+H3-G4 -> 10223628
A5: 40403 | B5: 361411.26 | C5: 11120346 | D5: 0.13 | E5: =+D5*C5*0.25 -> 361411.26 | F5: ='Get Rate for Iteration 8 '!$B$4 -> 0.14961373 | G5: =E5-((H4*0.25*F5)) -> -20987.539 | H5: =+H4-G5 -> 10244616
A6: 40495 | B6: 361411.26 | C6: 11120346 | D6: 0.13 | E6: =+D6*C6*0.25 -> 361411.26 | F6: ='Get Rate for Iteration 8 '!$B$4 -> 0.14961373 | G6: =E6-((H5*0.25*F6)) -> -21772.545 | H6: =+H5-G6 -> 10266389
A7: 40587 | B7: 361411.26 | C7: 11120346 | D7: 0.13 | E7: =+D7*C7*0.25 -> 361411.26 | F7: ='Get Rate for Iteration 8 '!$B$4 -> 0.14961373 | G7: =E7-((H6*0.25*F7)) -> -22586.913 | H7: =+H6-G7 -> 10288975
A8: 40676 | B8: 361411.26 | C8: 11120346 | D8: 0.13 | E8: =+D8*C8*0.25 -> 361411.26 | F8: ='Get Rate for Iteration 8 '!$B$4 -> 0.14961373 | G8: =E8-((H7*0.25*F8)) -> -23431.741 | H8: =+H7-G8 -> 10312407
A9: 40768 | B9: 361411.26 | C9: 11120346 | D9: 0.13 | E9: =+D9*C9*0.25 -> 361411.26 | F9: ='Get Rate for Iteration 8 '!$B$4 -> 0.14961373 | G9: =E9-((H8*0.25*F9)) -> -24308.168 | H9: =+H8-G9 -> 10336715
A10: 40860 | B10: 361411.26 | C10: 11120346 | D10: 0.13 | E10: =+D10*C10*0.25 -> 361411.26 | F10: ='Get Rate for Iteration 8 '!$B$4 -> 0.14961373 | G10: =E10-((H9*0.25*F10)) -> -25217.377 | H10: =+H9-G10 -> 10361933
A11: 40952 | B11: 361411.26 | C11: 11120346 | D11: 0.13 | E11: =+D11*C11*0.25 -> 361411.26 | F11: ='Get Rate for Iteration 8 '!$B$4 -> 0.14961373 | G11: =E11-((H10*0.25*F11)) -> -26160.594 | H11: =+H10-G11 -> 10388093
A12: 41042 | B12: 361411.26 | C12: 11120346 | D12: 0.13 | E12: =+D12*C12*0.25 -> 361411.26 | F12: ='Get Rate for Iteration 8 '!$B$4 -> 0.14961373 | G12: =E12-((H11*0.25*F12)) -> -27139.09 | H12: =+H11-G12 -> 10415232
A13: 41134 | B13: 361411.26 | C13: 11120346 | D13: 0.13 | E13: =+D13*C13*0.25 -> 361411.26 | F13: ='Get Rate for Iteration 8 '!$B$4 -> 0.14961373 | G13: =E13-((H12*0.25*F13)) -> -28154.185 | H13: =+H12-G13 -> 10443387
A14: 41226 | B14: 361411.26 | C14: 11120346 | D14: 0.13 | E14: =+D14*C14*0.25 -> 361411.26 | F14: ='Get Rate for Iteration 8 '!$B$4 -> 0.14961373 | G14: =E14-((H13*0.25*F14)) -> -29207.248 | H14: =+H13-G14 -> 10472594
... A29: 42595 | B29: 361411.26 | C29: 11120346 | D29: 0.13 | E29: =+D29*C29*0.25 -> 361411.26 | F29: ='Get Rate for Iteration 8 '!$B$4 -> 0.14961373 | G29: =E29-((H28*0.25*F29)) -> -50664.744 | H29: =+H28-G29 -> 11067729
A30: 42687 | B30: =+B29 -> 361411.26 | C30: 11120346 | D30: 0.13 | E30: =+D30*C30*0.25 -> 361411.26 | F30: ='Get Rate for Iteration 8 '!$B$4 -> 0.14961373 | G30: =E30-((H29*0.25*F30)) -> -52559.779 | H30: =+H29-G30 -> 11120288
F34: XIRR Function | G34: =H30-C2 -> -58.124335
F36: Tolerance | G36: 0.01

Sheet Get Rate for Iteration 9 
A1: A3 = A2-y2*(a2-a1)/y2-y1
A4: A3 | B4: =B5-B7*(B5-B6)/(B7-B8) -> 0.14961419 | C4: New Rate
A5: a2 | B5: ='Iteration 8 '!F2 -> 0.14961373 | C5: Rate from Iteration 2
A6: a1 | B6: ='Iteration 7 '!F2 -> 0.14968506 | C6: Rate from Iteration 1
A7: y2 | B7: ='Iteration 8 '!G34 -> -58.124335 | C7: Result from Iteration 2
A8: y1 | B8: ='Iteration 7 '!G34 -> 8919.4259 | C8: Result from Iteration1

Sheet Iteration 9 
A1: Date | B1: Cash Flow | C1: Face Value | D1: Coupon Rate | E1: Cash Payment | F1: Discount Rate | G1: Disc Amortization | H1: Carry Value
A2: 40130 | B2: -10183896 | C2: 11120346 | D2: 0.13 | F2: ='Get Rate for Iteration 9 '!$B$4 -> 0.14961419 | H2: =+B2*-1 -> 10183896
A3: 40222 | B3: 361411.26 | C3: 11120346 | D3: 0.13 | E3: =+D3*C3*0.25 -> 361411.26 | F3: ='Get Rate for Iteration 9 '!$B$4 -> 0.14961419 | G3: =E3-((H2*0.25*F3)) -> -19502.592 | H3: =+H2-G3 -> 10203399
A4: 40311 | B4: 361411.26 | C4: 11120346 | D4: 0.13 | E4: =+D4*C4*0.25 -> 361411.26 | F4: ='Get Rate for Iteration 9 '!$B$4 -> 0.14961419 | G4: =E4-((H3*0.25*F4)) -> -20232.058 | H4: =+H3-G4 -> 10223631
A5: 40403 | B5: 361411.26 | C5: 11120346 | D5: 0.13 | E5: =+D5*C5*0.25 -> 361411.26 | F5: ='Get Rate for Iteration 9 '!$B$4 -> 0.14961419 | G5: =E5-((H4*0.25*F5)) -> -20988.809 | H5: =+H4-G5 -> 10244620
A6: 40495 | B6: 361411.26 | C6: 11120346 | D6: 0.13 | E6: =+D6*C6*0.25 -> 361411.26 | F6: ='Get Rate for Iteration 9 '!$B$4 -> 0.14961419 | G6: =E6-((H5*0.25*F6)) -> -21773.865 | H6: =+H5-G6 -> 10266394
A7: 40587 | B7: 361411.26 | C7: 11120346 | D7: 0.13 | E7: =+D7*C7*0.25 -> 361411.26 | F7: ='Get Rate for Iteration 9 '!$B$4 -> 0.14961419 | G7: =E7-((H6*0.25*F7)) -> -22588.285 | H7: =+H6-G7 -> 10288982
A8: 40676 | B8: 361411.26 | C8: 11120346 | D8: 0.13 | E8: =+D8*C8*0.25 -> 361411.26 | F8: ='Get Rate for Iteration 9 '!$B$4 -> 0.14961419 | G8: =E8-((H7*0.25*F8)) -> -23433.167 | H8: =+H7-G8 -> 10312415
A9: 40768 | B9: 361411.26 | C9: 11120346 | D9: 0.13 | E9: =+D9*C9*0.25 -> 361411.26 | F9: ='Get Rate for Iteration 9 '!$B$4 -> 0.14961419 | G9: =E9-((H8*0.25*F9)) -> -24309.65 | H9: =+H8-G9 -> 10336725
A10: 40860 | B10: 361411.26 | C10: 11120346 | D10: 0.13 | E10: =+D10*C10*0.25 -> 361411.26 | F10: ='Get Rate for Iteration 9 '!$B$4 -> 0.14961419 | G10: =E10-((H9*0.25*F10)) -> -25218.917 | H10: =+H9-G10 -> 10361944
A11: 40952 | B11: 361411.26 | C11: 11120346 | D11: 0.13 | E11: =+D11*C11*0.25 -> 361411.26 | F11: ='Get Rate for Iteration 9 '!$B$4 -> 0.14961419 | G11: =E11-((H10*0.25*F11)) -> -26162.194 | H11: =+H10-G11 -> 10388106
A12: 41042 | B12: 361411.26 | C12: 11120346 | D12: 0.13 | E12: =+D12*C12*0.25 -> 361411.26 | F12: ='Get Rate for Iteration 9 '!$B$4 -> 0.14961419 | G12: =E12-((H11*0.25*F12)) -> -27140.753 | H12: =+H11-G12 -> 10415246
A13: 41134 | B13: 361411.26 | C13: 11120346 | D13: 0.13 | E13: =+D13*C13*0.25 -> 361411.26 | F13: ='Get Rate for Iteration 9 '!$B$4 -> 0.14961419 | G13: =E13-((H12*0.25*F13)) -> -28155.914 | H13: =+H12-G13 -> 10443402
A14: 41226 | B14: 361411.26 | C14: 11120346 | D14: 0.13 | E14: =+D14*C14*0.25 -> 361411.26 | F14: ='Get Rate for Iteration 9 '!$B$4 -> 0.14961419 | G14: =E14-((H13*0.25*F14)) -> -29209.045 | H14: =+H13-G14 -> 10472611
... A29: 42595 | B29: 361411.26 | C29: 11120346 | D29: 0.13 | E29: =+D29*C29*0.25 -> 361411.26 | F29: ='Get Rate for Iteration 9 '!$B$4 -> 0.14961419 | G29: =E29-((H28*0.25*F29)) -> -50667.945 | H29: =+H28-G29 -> 11067783
A30: 42687 | B30: =+B29 -> 361411.26 | C30: 11120346 | D30: 0.13 | E30: =+D30*C30*0.25 -> 361411.26 | F30: ='Get Rate for Iteration 9 '!$B$4 -> 0.14961419 | G30: =E30-((H29*0.25*F30)) -> -52563.106 | H30: =+H29-G30 -> 11120346
F34: XIRR Function | G34: =H30-C2 -> -0.015553886
F36: Tolerance | G36: 0.01

Sheet Get Rate for Iteration 10 
A1: A3 = A2-y2*(a2-a1)/y2-y1
A4: A3 | B4: =B5-B7*(B5-B6)/(B7-B8) -> 0.14961419 | C4: New Rate
A5: a2 | B5: ='Iteration 9 '!F2 -> 0.14961419 | C5: Rate from Iteration 2
A6: a1 | B6: ='Iteration 8 '!F2 -> 0.14961373 | C6: Rate from Iteration 1
A7: y2 | B7: ='Iteration 9 '!G34 -> -0.015553886 | C7: Result from Iteration 2
A8: y1 | B8: ='Iteration 8 '!G34 -> -58.124335 | C8: Result from Iteration1

Sheet Iteration 10 
A1: Date | B1: Cash Flow | C1: Face Value | D1: Coupon Rate | E1: Cash Payment | F1: Discount Rate | G1: Disc Amortization | H1: Carry Value
A2: 40130 | B2: -10183896 | C2: 11120346 | D2: 0.13 | F2: ='Get Rate for Iteration 10 '!$B$4 -> 0.14961419 | H2: =+B2*-1 -> 10183896
A3: 40222 | B3: 361411.26 | C3: 11120346 | D3: 0.13 | E3: =+D3*C3*0.25 -> 361411.26 | F3: ='Get Rate for Iteration 10 '!$B$4 -> 0.14961419 | G3: =E3-((H2*0.25*F3)) -> -19502.592 | H3: =+H2-G3 -> 10203399
A4: 40311 | B4: 361411.26 | C4: 11120346 | D4: 0.13 | E4: =+D4*C4*0.25 -> 361411.26 | F4: ='Get Rate for Iteration 10 '!$B$4 -> 0.14961419 | G4: =E4-((H3*0.25*F4)) -> -20232.059 | H4: =+H3-G4 -> 10223631
A5: 40403 | B5: 361411.26 | C5: 11120346 | D5: 0.13 | E5: =+D5*C5*0.25 -> 361411.26 | F5: ='Get Rate for Iteration 10 '!$B$4 -> 0.14961419 | G5: =E5-((H4*0.25*F5)) -> -20988.809 | H5: =+H4-G5 -> 10244620
A6: 40495 | B6: 361411.26 | C6: 11120346 | D6: 0.13 | E6: =+D6*C6*0.25 -> 361411.26 | F6: ='Get Rate for Iteration 10 '!$B$4 -> 0.14961419 | G6: =E6-((H5*0.25*F6)) -> -21773.865 | H6: =+H5-G6 -> 10266394
A7: 40587 | B7: 361411.26 | C7: 11120346 | D7: 0.13 | E7: =+D7*C7*0.25 -> 361411.26 | F7: ='Get Rate for Iteration 10 '!$B$4 -> 0.14961419 | G7: =E7-((H6*0.25*F7)) -> -22588.285 | H7: =+H6-G7 -> 10288982
A8: 40676 | B8: 361411.26 | C8: 11120346 | D8: 0.13 | E8: =+D8*C8*0.25 -> 361411.26 | F8: ='Get Rate for Iteration 10 '!$B$4 -> 0.14961419 | G8: =E8-((H7*0.25*F8)) -> -23433.167 | H8: =+H7-G8 -> 10312415
A9: 40768 | B9: 361411.26 | C9: 11120346 | D9: 0.13 | E9: =+D9*C9*0.25 -> 361411.26 | F9: ='Get Rate for Iteration 10 '!$B$4 -> 0.14961419 | G9: =E9-((H8*0.25*F9)) -> -24309.651 | H9: =+H8-G9 -> 10336725
A10: 40860 | B10: 361411.26 | C10: 11120346 | D10: 0.13 | E10: =+D10*C10*0.25 -> 361411.26 | F10: ='Get Rate for Iteration 10 '!$B$4 -> 0.14961419 | G10: =E10-((H9*0.25*F10)) -> -25218.918 | H10: =+H9-G10 -> 10361944
A11: 40952 | B11: 361411.26 | C11: 11120346 | D11: 0.13 | E11: =+D11*C11*0.25 -> 361411.26 | F11: ='Get Rate for Iteration 10 '!$B$4 -> 0.14961419 | G11: =E11-((H10*0.25*F11)) -> -26162.195 | H11: =+H10-G11 -> 10388106
A12: 41042 | B12: 361411.26 | C12: 11120346 | D12: 0.13 | E12: =+D12*C12*0.25 -> 361411.26 | F12: ='Get Rate for Iteration 10 '!$B$4 -> 0.14961419 | G12: =E12-((H11*0.25*F12)) -> -27140.754 | H12: =+H11-G12 -> 10415246
A13: 41134 | B13: 361411.26 | C13: 11120346 | D13: 0.13 | E13: =+D13*C13*0.25 -> 361411.26 | F13: ='Get Rate for Iteration 10 '!$B$4 -> 0.14961419 | G13: =E13-((H12*0.25*F13)) -> -28155.914 | H13: =+H12-G13 -> 10443402
A14: 41226 | B14: 361411.26 | C14: 11120346 | D14: 0.13 | E14: =+D14*C14*0.25 -> 361411.26 | F14: ='Get Rate for Iteration 10 '!$B$4 -> 0.14961419 | G14: =E14-((H13*0.25*F14)) -> -29209.045 | H14: =+H13-G14 -> 10472611
... A29: 42595 | B29: 361411.26 | C29: 11120346 | D29: 0.13 | E29: =+D29*C29*0.25 -> 361411.26 | F29: ='Get Rate for Iteration 10 '!$B$4 -> 0.14961419 | G29: =E29-((H28*0.25*F29)) -> -50667.946 | H29: =+H28-G29 -> 11067783
A30: 42687 | B30: =+B29 -> 361411.26 | C30: 11120346 | D30: 0.13 | E30: =+D30*C30*0.25 -> 361411.26 | F30: ='Get Rate for Iteration 10 '!$B$4 -> 0.14961419 | G30: =E30-((H29*0.25*F30)) -> -52563.107 | H30: =+H29-G30 -> 11120346
F34: XIRR Function | G34: =H30-C2 -> 2.4214387e-08
F36: Tolerance | G36: 0.01
