Workbook

Sheet Terms 
A1: Settlement | B1: 40130 | D1: Cost | E1: 10183896
A2: Maturity | B2: 42687 | D2: Face Value | E2: 11120346
A3: Rate | B3: 0.13
A4: Price | B4: =+E1/E2*100 -> 91.578947
A5: Redemption | B5: 100
A6: Coupon Frequency | B6: 4
A7: Day Basis | B7: 0
A8: Yield | B8: =YIELD(B1,B2,B3,B4,B5,B6,B7) -> 0.14961419

Sheet XIRR 
A1: Date | B1: Cash Flow | C1: XIRR
A2: 40130 | B2: -10183896 | C2: =XIRR(B2:B30,A2:A30) -> 0.15812421
A3: 40222 | B3: 361411.26
A4: 40311 | B4: 361411.26
A5: 40403 | B5: 361411.26
A6: 40495 | B6: 361411.26
A7: 40587 | B7: 361411.26
A8: 40676 | B8: 361411.26
A9: 40768 | B9: 361411.26
A10: 40860 | B10: 361411.26
A11: 40952 | B11: 361411.26
A12: 41042 | B12: 361411.26
A13: 41134 | B13: 361411.26
A14: 41226 | B14: 361411.26
... A30: 42687 | B30: 11481758

Sheet Carry Value Proof 
A1: Day Basis = 30/360 | E1: 0.15821962 | J1: Day Basis = 30/360 | N1: 0.14961419
A2: Date | B2: Cash Flow | C2: Face Value | D2: Carry Value | E2: Effective Interest Rate | F2: Disc Amortization | J2: Date | K2: Cash Flow | L2: Face Value | M2: Carry Value | N2: Effective Interest Rate | O2: Disc Amortization
A3: 40130 | B3: -10183896 | C3: 11120346 | D3: 10183896 | E3: =+E1 -> 0.15821962 | J3: 40130 | K3: -10183896 | L3: 11120346 | M3: 10183896 | N3: =+N1 -> 0.14961419
A4: 40222 | B4: 361411.26 | D4: =+D3+F4 -> 10225308 | F4: =(0.25*$E$3*D3)-B4 -> 41411.778 | J4: 40222 | K4: 361411.26 | M4: =+M3+O4 -> 10203399 | O4: =(0.25*$N$3*M3)-K4 -> 19502.592
A5: 40311 | B5: 361411.26 | D5: =+D4+F5 -> 10268358 | F5: =(0.25*$E$3*D4)-B5 -> 43049.817 | J5: 40311 | K5: 361411.26 | M5: =+M4+O5 -> 10223631 | O5: =(0.25*$N$3*M4)-K5 -> 20232.059
A6: 40403 | B6: 361411.26 | D6: =+D5+F6 -> 10313110 | F6: =(0.25*$E$3*D5)-B6 -> 44752.648 | J6: 40403 | K6: 361411.26 | M6: =+M5+O6 -> 10244620 | O6: =(0.25*$N$3*M5)-K6 -> 20988.809
A7: 40495 | B7: 361411.26 | D7: =+D6+F7 -> 10359633 | F7: =(0.25*$E$3*D6)-B7 -> 46522.835 | J7: 40495 | K7: 361411.26 | M7: =+M6+O7 -> 10266394 | O7: =(0.25*$N$3*M6)-K7 -> 21773.865
A8: 40587 | B8: 361411.26 | D8: =+D7+F8 -> 10407996 | F8: =(0.25*$E$3*D7)-B8 -> 48363.041 | J8: 40587 | K8: 361411.26 | M8: =+M7+O8 -> 10288982 | O8: =(0.25*$N$3*M7)-K8 -> 22588.285
A9: 40676 | B9: 361411.26 | D9: =+D8+F9 -> 10458272 | F9: =(0.25*$E$3*D8)-B9 -> 50276.037 | J9: 40676 | K9: 361411.26 | M9: =+M8+O9 -> 10312415 | O9: =(0.25*$N$3*M8)-K9 -> 23433.167
A10: 40768 | B10: 361411.26 | D10: =+D9+F10 -> 10510537 | F10: =(0.25*$E$3*D9)-B10 -> 52264.701 | J10: 40768 | K10: 361411.26 | M10: =+M9+O10 -> 10336725 | O10: =(0.25*$N$3*M9)-K10 -> 24309.651
A11: 40860 | B11: 361411.26 | D11: =+D10+F11 -> 10564869 | F11: =(0.25*$E$3*D10)-B11 -> 54332.026 | J11: 40860 | K11: 361411.26 | M11: =+M10+O11 -> 10361944 | O11: =(0.25*$N$3*M10)-K11 -> 25218.918
A12: 40952 | B12: 361411.26 | D12: =+D11+F12 -> 10621350 | F12: =(0.25*$E$3*D11)-B12 -> 56481.124 | J12: 40952 | K12: 361411.26 | M12: =+M11+O12 -> 10388106 | O12: =(0.25*$N$3*M11)-K12 -> 26162.195
A13: 41042 | B13: 361411.26 | D13: =+D12+F13 -> 10680065 | F13: =(0.25*$E$3*D12)-B13 -> 58715.229 | J13: 41042 | K13: 361411.26 | M13: =+M12+O13 -> 10415246 | O13: =(0.25*$N$3*M12)-K13 -> 27140.754
A14: 41134 | B14: 361411.26 | D14: =+D13+F14 -> 10741103 | F14: =(0.25*$E$3*D13)-B14 -> 61037.705 | J14: 41134 | K14: 361411.26 | M14: =+M13+O14 -> 10443402 | O14: =(0.25*$N$3*M13)-K14 -> 28155.914
A15: 41226 | B15: 361411.26 | D15: =+D14+F15 -> 10804555 | F15: =(0.25*$E$3*D14)-B15 -> 63452.045 | J15: 41226 | K15: 361411.26 | M15: =+M14+O15 -> 10472611 | O15: =(0.25*$N$3*M14)-K15 -> 29209.045
... A19: 41591 | B19: 361411.26 | D19: =+D18+F19 -> 11084474 | F19: =(0.25*$E$3*D18)-B19 -> 74102.925 | J19: 41591 | K19: 361411.26 | M19: =+M18+O19 -> 10600789 | O19: =(0.25*$N$3*M18)-K19 -> 33830.489
A20: 41683 | B20: 361411.26 | D20: =+D19+F20 -> 11161508 | F20: =(0.25*$E$3*D19)-B20 -> 77034.059 | G20: Discount Fully Amortized | J20: 41683 | K20: 361411.26 | M20: =+M19+O20 -> 10635885 | O20: =(0.25*$N$3*M19)-K20 -> 35095.87
A21: 41772 | B21: 361411.26 | D21: =+D20+F21 -> 11241590 | F21: =(0.25*$E$3*D20)-B21 -> 80081.134 | J21: 41772 | K21: 361411.26 | M21: =+M20+O21 -> 10672294 | O21: =(0.25*$N$3*M20)-K21 -> 36408.58
A22: 41864 | B22: 361411.26 | D22: =+D21+F22 -> 11324838 | F22: =(0.25*$E$3*D21)-B22 -> 83248.735 | J22: 41864 | K22: 361411.26 | M22: =+M21+O22 -> 10710064 | O22: =(0.25*$N$3*M21)-K22 -> 37770.39
A23: 41956 | B23: 361411.26 | D23: =+D22+F23 -> 11411380 | F23: =(0.25*$E$3*D22)-B23 -> 86541.631 | J23: 41956 | K23: 361411.26 | M23: =+M22+O23 -> 10749247 | O23: =(0.25*$N$3*M22)-K23 -> 39183.136
A24: 42048 | B24: 361411.26 | D24: =+D23+F24 -> 11501345 | F24: =(0.25*$E$3*D23)-B24 -> 89964.777 | J24: 42048 | K24: 361411.26 | M24: =+M23+O24 -> 10789896 | O24: =(0.25*$N$3*M23)-K24 -> 40648.725
A25: 42137 | B25: 361411.26 | D25: =+D24+F25 -> 11594868 | F25: =(0.25*$E$3*D24)-B25 -> 93523.325 | J25: 42137 | K25: 361411.26 | M25: =+M24+O25 -> 10832065 | O25: =(0.25*$N$3*M24)-K25 -> 42169.131
A26: 42229 | B26: 361411.26 | D26: =+D25+F26 -> 11692091 | F26: =(0.25*$E$3*D25)-B26 -> 97222.631 | J26: 42229 | K26: 361411.26 | M26: =+M25+O26 -> 10875811 | O26: =(0.25*$N$3*M25)-K26 -> 43746.406
A27: 42321 | B27: 361411.26 | D27: =+D26+F27 -> 11793159 | F27: =(0.25*$E$3*D26)-B27 -> 101068.26 | J27: 42321 | K27: 361411.26 | M27: =+M26+O27 -> 10921194 | O27: =(0.25*$N$3*M26)-K27 -> 45382.677
A28: 42413 | B28: 361411.26 | D28: =+D27+F28 -> 11898225 | F28: =(0.25*$E$3*D27)-B28 -> 105066.01 | J28: 42413 | K28: 361411.26 | M28: =+M27+O28 -> 10968274 | O28: =(0.25*$N$3*M27)-K28 -> 47080.15
A29: 42503 | B29: 361411.26 | D29: =+D28+F29 -> 12007447 | F29: =(0.25*$E$3*D28)-B29 -> 109221.88 | J29: 42503 | K29: 361411.26 | M29: =+M28+O29 -> 11017115 | O29: =(0.25*$N$3*M28)-K29 -> 48841.115
A30: 42595 | B30: 361411.26 | D30: =+D29+F30 -> 12120989 | F30: =(0.25*$E$3*D29)-B30 -> 113542.15 | J30: 42595 | K30: 361411.26 | M30: =+M29+O30 -> 11067783 | O30: =(0.25*$N$3*M29)-K30 -> 50667.946
A31: 42687 | B31: 361411.26 | D31: =+D30+F31 -> 12239022 | F31: =(0.25*$E$3*D30)-B31 -> 118033.29 | J31: 42687 | K31: 361411.26 | M31: =+M30+O31 -> 11120346 | O31: =(0.25*$N$3*M30)-K31 -> 52563.107
F32: =SUM(F4:F31) -> 2055126 | O32: =SUM(O4:O31) -> 936450.23

Sheet Iteration 1
A1: Date | B1: Cash Flow | C1: Rate | D1: Rate ^ Interval | E1: IRR Function | F1: RF IRR Function | G1: Period day fraction
A2: 40130 | B2: -10183896 | C2: 0 | D2: 1 | E2: =B2/D2 -> -10183896 | F2: =E2 -> -10183896 | G2: =1-1 -> 0
A3: 40222 | B3: 361411.26 | C3: 0 | D3: 1 | E3: =B3/D3 -> 361411.26 | F3: =F2+E3 -> -9822484.9 | G3: 0.25
A4: 40311 | B4: 361411.26 | C4: 0 | D4: 1 | E4: =B4/D4 -> 361411.26 | F4: =F3+E4 -> -9461073.7 | G4: 0.5
A5: 40403 | B5: 361411.26 | C5: 0 | D5: 1 | E5: =B5/D5 -> 361411.26 | F5: =F4+E5 -> -9099662.4 | G5: 0.75
A6: 40495 | B6: 361411.26 | C6: 0 | D6: 1 | E6: =B6/D6 -> 361411.26 | F6: =F5+E6 -> -8738251.2 | G6: 1
A7: 40587 | B7: 361411.26 | C7: 0 | D7: 1 | E7: =B7/D7 -> 361411.26 | F7: =F6+E7 -> -8376839.9 | G7: 1.25
A8: 40676 | B8: 361411.26 | C8: 0 | D8: 1 | E8: =B8/D8 -> 361411.26 | F8: =F7+E8 -> -8015428.6 | G8: 1.5
A9: 40768 | B9: 361411.26 | C9: 0 | D9: 1 | E9: =B9/D9 -> 361411.26 | F9: =F8+E9 -> -7654017.4 | G9: 1.75
A10: 40860 | B10: 361411.26 | C10: 0 | D10: 1 | E10: =B10/D10 -> 361411.26 | F10: =F9+E10 -> -7292606.1 | G10: 2
A11: 40952 | B11: 361411.26 | C11: 0 | D11: 1 | E11: =B11/D11 -> 361411.26 | F11: =F10+E11 -> -6931194.9 | G11: 2.25
A12: 41042 | B12: 361411.26 | C12: 0 | D12: 1 | E12: =B12/D12 -> 361411.26 | F12: =F11+E12 -> -6569783.6 | G12: 2.5
A13: 41134 | B13: 361411.26 | C13: 0 | D13: 1 | E13: =B13/D13 -> 361411.26 | F13: =F12+E13 -> -6208372.4 | G13: 2.75
A14: 41226 | B14: 361411.26 | C14: 0 | D14: 1 | E14: =B14/D14 -> 361411.26 | F14: =F13+E14 -> -5846961.1 | G14: 3
... A30: 42687 | B30: 11481758 | C30: 0 | D30: 1 | E30: =B30/D30 -> 11481758 | F30: =F29+E30 -> 11055965 | G30: 7

Sheet Iteration 2 
B1: Cash Flow | C1: Rate | D1: Rate ^ Interval | E1: IRR Function | F1: RF IRR Function | G1: Period Day Fraction
A2: 40130 | B2: -10183896 | C2: =0.05-0.05*0.75 -> 0.0125 | D2: =(1+C2)^G2 -> 1 | E2: =B2/D2 -> -10183896 | F2: =E2 -> -10183896 | G2: =1-1 -> 0
A3: 40222 | B3: 361411.26 | C3: =0.05-0.05*0.75 -> 0.0125 | D3: =(1+C3)^G3 -> 1.0031105 | E3: =+B3/D3 -> 360290.59 | F3: =F2+E3 -> -9823605.6 | G3: 0.25
A4: 40311 | B4: 361411.26 | C4: =0.05-0.05*0.75 -> 0.0125 | D4: =(1+C4)^G4 -> 1.0062306 | E4: =B4/D4 -> 359173.4 | F4: =F3+E4 -> -9464432.2 | G4: 0.5
A5: 40403 | B5: 361411.26 | C5: =0.05-0.05*0.75 -> 0.0125 | D5: =(1+C5)^G5 -> 1.0093604 | E5: =B5/D5 -> 358059.67 | F5: =F4+E5 -> -9106372.5 | G5: 0.75
A6: 40495 | B6: 361411.26 | C6: =0.05-0.05*0.75 -> 0.0125 | D6: =(1+C6)^G6 -> 1.0125 | E6: =B6/D6 -> 356949.39 | F6: =F5+E6 -> -8749423.2 | G6: 1
A7: 40587 | B7: 361411.26 | C7: =0.05-0.05*0.75 -> 0.0125 | D7: =(1+C7)^G7 -> 1.0156493 | E7: =B7/D7 -> 355842.56 | F7: =F6+E7 -> -8393580.6 | G7: 1.25
A8: 40676 | B8: 361411.26 | C8: =0.05-0.05*0.75 -> 0.0125 | D8: =(1+C8)^G8 -> 1.0188085 | E8: =B8/D8 -> 354739.16 | F8: =F7+E8 -> -8038841.4 | G8: 1.5
A9: 40768 | B9: 361411.26 | C9: =0.05-0.05*0.75 -> 0.0125 | D9: =(1+C9)^G9 -> 1.0219774 | E9: =B9/D9 -> 353639.18 | F9: =F8+E9 -> -7685202.3 | G9: 1.75
A10: 40860 | B10: 361411.26 | C10: =0.05-0.05*0.75 -> 0.0125 | D10: =(1+C10)^G10 -> 1.0251562 | E10: =B10/D10 -> 352542.61 | F10: =F9+E10 -> -7332659.7 | G10: 2
A11: 40952 | B11: 361411.26 | C11: =0.05-0.05*0.75 -> 0.0125 | D11: =(1+C11)^G11 -> 1.028345 | E11: =B11/D11 -> 351449.44 | F11: =F10+E11 -> -6981210.2 | G11: 2.25
A12: 41042 | B12: 361411.26 | C12: =0.05-0.05*0.75 -> 0.0125 | D12: =(1+C12)^G12 -> 1.0315436 | E12: =B12/D12 -> 350359.66 | F12: =F11+E12 -> -6630850.5 | G12: 2.5
A13: 41134 | B13: 361411.26 | C13: =0.05-0.05*0.75 -> 0.0125 | D13: =(1+C13)^G13 -> 1.0347522 | E13: =B13/D13 -> 349273.26 | F13: =F12+E13 -> -6281577.3 | G13: 2.75
A14: 41226 | B14: 361411.26 | C14: =0.05-0.05*0.75 -> 0.0125 | D14: =(1+C14)^G14 -> 1.0379707 | E14: =B14/D14 -> 348190.23 | F14: =F13+E14 -> -5933387.1 | G14: 3
A15: 41318 | B15: 361411.26 | C15: =0.05-0.05*0.75 -> 0.0125 | D15: =(1+C15)^G15 -> 1.0411993 | E15: =B15/D15 -> 347110.56 | F15: =F14+E15 -> -5586276.5 | G15: 3.25
... A30: 42687 | B30: 11481758 | C30: =0.05-0.05*0.75 -> 0.0125 | D30: =(1+C30)^G30 -> 1.0908505 | E30: =B30/D30 -> 10525510 | F30: =F29+E30 -> 9687271.9 | G30: 7

Sheet Iteration 3 
B1: Cash Flow | C1: Rate | D1: Rate ^ Interval | E1: IRR Function | F1: RF IRR Function | G1: Period Day Fraction
A2: 40130 | B2: -10183896 | C2: =0.05+0.05*0.75 -> 0.0875 | D2: =(1+C2)^G2 -> 1 | E2: =B2/D2 -> -10183896 | F2: =E2 -> -10183896 | G2: =1-1 -> 0
A3: 40222 | B3: 361411.26 | C3: =0.05+0.05*0.75 -> 0.0875 | D3: =(1+C3)^G3 -> 1.0211918 | E3: =B3/D3 -> 353911.24 | F3: =F2+E3 -> -9829985 | G3: 0.25
A4: 40311 | B4: 361411.26 | C4: =0.05+0.05*0.75 -> 0.0875 | D4: =(1+C4)^G4 -> 1.0428327 | E4: =B4/D4 -> 346566.87 | F4: =F3+E4 -> -9483418.1 | G4: 0.5
A5: 40403 | B5: 361411.26 | C5: =0.05+0.05*0.75 -> 0.0875 | D5: =(1+C5)^G5 -> 1.0649322 | E5: =B5/D5 -> 339374.91 | F5: =F4+E5 -> -9144043.2 | G5: 0.75
A6: 40495 | B6: 361411.26 | C6: =0.05+0.05*0.75 -> 0.0875 | D6: =(1+C6)^G6 -> 1.0875 | E6: =B6/D6 -> 332332.19 | F6: =F5+E6 -> -8811711 | G6: 1
A7: 40587 | B7: 361411.26 | C7: =0.05+0.05*0.75 -> 0.0875 | D7: =(1+C7)^G7 -> 1.1105461 | E7: =B7/D7 -> 325435.63 | F7: =F6+E7 -> -8486275.4 | G7: 1.25
A8: 40676 | B8: 361411.26 | C8: =0.05+0.05*0.75 -> 0.0875 | D8: =(1+C8)^G8 -> 1.1340805 | E8: =B8/D8 -> 318682.18 | F8: =F7+E8 -> -8167593.2 | G8: 1.5
A9: 40768 | B9: 361411.26 | C9: =0.05+0.05*0.75 -> 0.0875 | D9: =(1+C9)^G9 -> 1.1581137 | E9: =B9/D9 -> 312068.88 | F9: =F8+E9 -> -7855524.3 | G9: 1.75
A10: 40860 | B10: 361411.26 | C10: =0.05+0.05*0.75 -> 0.0875 | D10: =(1+C10)^G10 -> 1.1826562 | E10: =B10/D10 -> 305592.82 | F10: =F9+E10 -> -7549931.5 | G10: 2
A11: 40952 | B11: 361411.26 | C11: =0.05+0.05*0.75 -> 0.0875 | D11: =(1+C11)^G11 -> 1.2077189 | E11: =B11/D11 -> 299251.15 | F11: =F10+E11 -> -7250680.3 | G11: 2.25
A12: 41042 | B12: 361411.26 | C12: =0.05+0.05*0.75 -> 0.0875 | D12: =(1+C12)^G12 -> 1.2333126 | E12: =B12/D12 -> 293041.09 | F12: =F11+E12 -> -6957639.2 | G12: 2.5
A13: 41134 | B13: 361411.26 | C13: =0.05+0.05*0.75 -> 0.0875 | D13: =(1+C13)^G13 -> 1.2594487 | E13: =B13/D13 -> 286959.89 | F13: =F12+E13 -> -6670679.3 | G13: 2.75
A14: 41226 | B14: 361411.26 | C14: =0.05+0.05*0.75 -> 0.0875 | D14: =(1+C14)^G14 -> 1.2861387 | E14: =B14/D14 -> 281004.89 | F14: =F13+E14 -> -6389674.5 | G14: 3
... A30: 42687 | B30: 11481758 | C30: =0.05+0.05*0.75 -> 0.0875 | D30: =(1+C30)^G30 -> 1.798891 | E30: =B30/D30 -> 6382686.6 | F30: =F29+E30 -> 3571731.5 | G30: 7

Sheet Get Rate for Iteration 4
A1: A3 = A2-y2*(a2-a1)/y2-y1
A4: A3 | B4: =B5-B7*(B5-B6)/(B7-B8) -> 0.13130314 | C4: New Rate
A5: a2 | B5: 0.0875 | C5: Rate from Iteration 2
A6: a1 | B6: 0.0125 | C6: Rate from Iteration 1
A7: y2 | B7: ='Iteration 3 '!F30 -> 3571731.5 | C7: Result from Iteration 2
A8: y1 | B8: ='Iteration 2 '!F30 -> 9687271.9 | C8: Result from Iteration1

Sheet Iteration 4 
B1: Cash Flow | C1: Rate | D1: Rate ^ Interval | E1: IRR Function | F1: RF IRR Function | G1: Period Day Fraction
A2: 40130 | B2: -10183896 | C2: ='Get Rate for Iteration 4'!$B$4 -> 0.13130314 | D2: =(1+C2)^G2 -> 1 | E2: =B2/D2 -> -10183896 | F2: =E2 -> -10183896 | G2: =1-1 -> 0
A3: 40222 | B3: 361411.26 | C3: ='Get Rate for Iteration 4'!$B$4 -> 0.13130314 | D3: =(1+C3)^G3 -> 1.0313231 | E3: =B3/D3 -> 350434.56 | F3: =F2+E3 -> -9833461.6 | G3: 0.25
A4: 40311 | B4: 361411.26 | C4: ='Get Rate for Iteration 4'!$B$4 -> 0.13130314 | D4: =(1+C4)^G4 -> 1.0636273 | E4: =B4/D4 -> 339791.24 | F4: =F3+E4 -> -9493670.4 | G4: 0.5
A5: 40403 | B5: 361411.26 | C5: ='Get Rate for Iteration 4'!$B$4 -> 0.13130314 | D5: =(1+C5)^G5 -> 1.0969435 | E5: =B5/D5 -> 329471.18 | F5: =F4+E5 -> -9164199.2 | G5: 0.75
A6: 40495 | B6: 361411.26 | C6: ='Get Rate for Iteration 4'!$B$4 -> 0.13130314 | D6: =(1+C6)^G6 -> 1.1313031 | E6: =B6/D6 -> 319464.56 | F6: =F5+E6 -> -8844734.7 | G6: 1
A7: 40587 | B7: 361411.26 | C7: ='Get Rate for Iteration 4'!$B$4 -> 0.13130314 | D7: =(1+C7)^G7 -> 1.1667391 | E7: =B7/D7 -> 309761.86 | F7: =F6+E7 -> -8534972.8 | G7: 1.25
A8: 40676 | B8: 361411.26 | C8: ='Get Rate for Iteration 4'!$B$4 -> 0.13130314 | D8: =(1+C8)^G8 -> 1.203285 | E8: =B8/D8 -> 300353.84 | F8: =F7+E8 -> -8234619 | G8: 1.5
A9: 40768 | B9: 361411.26 | C9: ='Get Rate for Iteration 4'!$B$4 -> 0.13130314 | D9: =(1+C9)^G9 -> 1.2409756 | E9: =B9/D9 -> 291231.56 | F9: =F8+E9 -> -7943387.4 | G9: 1.75
A10: 40860 | B10: 361411.26 | C10: ='Get Rate for Iteration 4'!$B$4 -> 0.13130314 | D10: =(1+C10)^G10 -> 1.2798468 | E10: =B10/D10 -> 282386.35 | F10: =F9+E10 -> -7661001.1 | G10: 2
A11: 40952 | B11: 361411.26 | C11: ='Get Rate for Iteration 4'!$B$4 -> 0.13130314 | D11: =(1+C11)^G11 -> 1.3199356 | E11: =B11/D11 -> 273809.77 | F11: =F10+E11 -> -7387191.3 | G11: 2.25
A12: 41042 | B12: 361411.26 | C12: ='Get Rate for Iteration 4'!$B$4 -> 0.13130314 | D12: =(1+C12)^G12 -> 1.3612801 | E12: =B12/D12 -> 265493.69 | F12: =F11+E12 -> -7121697.6 | G12: 2.5
A13: 41134 | B13: 361411.26 | C13: ='Get Rate for Iteration 4'!$B$4 -> 0.13130314 | D13: =(1+C13)^G13 -> 1.4039196 | E13: =B13/D13 -> 257430.17 | F13: =F12+E13 -> -6864267.4 | G13: 2.75
A14: 41226 | B14: 361411.26 | C14: ='Get Rate for Iteration 4'!$B$4 -> 0.13130314 | D14: =(1+C14)^G14 -> 1.4478947 | E14: =B14/D14 -> 249611.56 | F14: =F13+E14 -> -6614655.9 | G14: 3
... A30: 42687 | B30: 11481758 | C30: ='Get Rate for Iteration 4'!$B$4 -> 0.13130314 | D30: =(1+C30)^G30 -> 2.3716628 | E30: =B30/D30 -> 4841226.8 | F30: =F29+E30 -> 1178099.3 | G30: 7

Sheet Get Rate for Iteration 5
A1: A3 = A2-y2*(a2-a1)/y2-y1
A4: A3 | B4: =B5-B7*(B5-B6)/(B7-B8) -> 0.15286219 | C4: New Rate
A5: a2 | B5: ='Iteration 4 '!C2 -> 0.13130314 | C5: Rate From Iteration 4
A6: a1 | B6: ='Iteration 3 '!C2 -> 0.0875 | C6: Rate from iteration 3
A7: y2 | B7: ='Iteration 4 '!F30 -> 1178099.3 | C7: result from iteration 4
A8: y1 | B8: ='Iteration 3 '!F30 -> 3571731.5 | C8: result from iteration 3

Sheet Iteration 5 
B1: Cash Flow | C1: Rate | D1: Rate ^ Interval | E1: IRR Function | F1: RF IRR Function | G1: Period Day count
A2: 40130 | B2: -10183896 | C2: ='Get Rate for Iteration 5'!$B$4 -> 0.15286219 | D2: =(1+C2)^G2 -> 1 | E2: =B2/D2 -> -10183896 | F2: =E2 -> -10183896 | G2: =1-1 -> 0
A3: 40222 | B3: 361411.26 | C3: ='Get Rate for Iteration 5'!$B$4 -> 0.15286219 | D3: =(1+C3)^G3 -> 1.0362018 | E3: =B3/D3 -> 348784.62 | F3: =F2+E3 -> -9835111.6 | G3: 0.25
A4: 40311 | B4: 361411.26 | C4: ='Get Rate for Iteration 5'!$B$4 -> 0.15286219 | D4: =(1+C4)^G4 -> 1.0737142 | E4: =B4/D4 -> 336599.12 | F4: =F3+E4 -> -9498512.5 | G4: 0.5
A5: 40403 | B5: 361411.26 | C5: ='Get Rate for Iteration 5'!$B$4 -> 0.15286219 | D5: =(1+C5)^G5 -> 1.1125846 | E5: =B5/D5 -> 324839.35 | F5: =F4+E5 -> -9173673.1 | G5: 0.75
A6: 40495 | B6: 361411.26 | C6: ='Get Rate for Iteration 5'!$B$4 -> 0.15286219 | D6: =(1+C6)^G6 -> 1.1528622 | E6: =B6/D6 -> 313490.42 | F6: =F5+E6 -> -8860182.7 | G6: 1
A7: 40587 | B7: 361411.26 | C7: ='Get Rate for Iteration 5'!$B$4 -> 0.15286219 | D7: =(1+C7)^G7 -> 1.1945979 | E7: =B7/D7 -> 302538 | F7: =F6+E7 -> -8557644.7 | G7: 1.25
A8: 40676 | B8: 361411.26 | C8: ='Get Rate for Iteration 5'!$B$4 -> 0.15286219 | D8: =(1+C8)^G8 -> 1.2378445 | E8: =B8/D8 -> 291968.22 | F8: =F7+E8 -> -8265676.5 | G8: 1.5
A9: 40768 | B9: 361411.26 | C9: ='Get Rate for Iteration 5'!$B$4 -> 0.15286219 | D9: =(1+C9)^G9 -> 1.2826567 | E9: =B9/D9 -> 281767.72 | F9: =F8+E9 -> -7983908.7 | G9: 1.75
A10: 40860 | B10: 361411.26 | C10: ='Get Rate for Iteration 5'!$B$4 -> 0.15286219 | D10: =(1+C10)^G10 -> 1.3290912 | E10: =B10/D10 -> 271923.59 | F10: =F9+E10 -> -7711985.2 | G10: 2
A11: 40952 | B11: 361411.26 | C11: ='Get Rate for Iteration 5'!$B$4 -> 0.15286219 | D11: =(1+C11)^G11 -> 1.3772068 | E11: =B11/D11 -> 262423.39 | F11: =F10+E11 -> -7449561.8 | G11: 2.25
A12: 41042 | B12: 361411.26 | C12: ='Get Rate for Iteration 5'!$B$4 -> 0.15286219 | D12: =(1+C12)^G12 -> 1.4270641 | E12: =B12/D12 -> 253255.09 | F12: =F11+E12 -> -7196306.7 | G12: 2.5
A13: 41134 | B13: 361411.26 | C13: ='Get Rate for Iteration 5'!$B$4 -> 0.15286219 | D13: =(1+C13)^G13 -> 1.4787265 | E13: =B13/D13 -> 244407.11 | F13: =F12+E13 -> -6951899.6 | G13: 2.75
A14: 41226 | B14: 361411.26 | C14: ='Get Rate for Iteration 5'!$B$4 -> 0.15286219 | D14: =(1+C14)^G14 -> 1.532259 | E14: =B14/D14 -> 235868.25 | F14: =F13+E14 -> -6716031.3 | G14: 3
... A30: 42687 | B30: 11481758 | C30: ='Get Rate for Iteration 5'!$B$4 -> 0.15286219 | D30: =(1+C30)^G30 -> 2.7067103 | E30: =B30/D30 -> 4241960.3 | F30: =F29+E30 -> 219447.37 | G30: 7

Sheet Get Rate for Iteration 6
A1: A3 = A2-y2*(a2-a1)/y2-y1
A4: A3 | B4: =B5-B7*(B5-B6)/(B7-B8) -> 0.15779733 | C4: New Rate
A5: a2 | B5: ='Iteration 5 '!C2 -> 0.15286219 | C5: rate from iteration 5
A6: a1 | B6: ='Iteration 4 '!C2 -> 0.13130314 | C6: rate from iteration 4
A7: y2 | B7: ='Iteration 5 '!F30 -> 219447.37 | C7: result from iteration 5
A8: y1 | B8: ='Iteration 4 '!F30 -> 1178099.3 | C8: result from iteration 4

Sheet Iteration 6
B1: Cash Flow | C1: Rate | D1: Rate ^ Interval | E1: IRR Function | F1: RF IRR Function | G1: Period Day Fraction
A2: 40130 | B2: -10183896 | C2: ='Get Rate for Iteration 6'!$B$4 -> 0.15779733 | D2: =(1+C2)^G2 -> 1 | E2: =B2/D2 -> -10183896 | F2: =E2 -> -10183896 | G2: =1-1 -> 0
A3: 40222 | B3: 361411.26 | C3: ='Get Rate for Iteration 6'!$B$4 -> 0.15779733 | D3: =(1+C3)^G3 -> 1.037309 | E3: =B3/D3 -> 348412.35 | F3: =F2+E3 -> -9835483.8 | G3: 0.25
A4: 40311 | B4: 361411.26 | C4: ='Get Rate for Iteration 6'!$B$4 -> 0.15779733 | D4: =(1+C4)^G4 -> 1.0760099 | E4: =B4/D4 -> 335880.98 | F4: =F3+E4 -> -9499602.9 | G4: 0.5
A5: 40403 | B5: 361411.26 | C5: ='Get Rate for Iteration 6'!$B$4 -> 0.15779733 | D5: =(1+C5)^G5 -> 1.1161547 | E5: =B5/D5 -> 323800.32 | F5: =F4+E5 -> -9175802.6 | G5: 0.75
A6: 40495 | B6: 361411.26 | C6: ='Get Rate for Iteration 6'!$B$4 -> 0.15779733 | D6: =(1+C6)^G6 -> 1.1577973 | E6: =B6/D6 -> 312154.17 | F6: =F5+E6 -> -8863648.4 | G6: 1
A7: 40587 | B7: 361411.26 | C7: ='Get Rate for Iteration 6'!$B$4 -> 0.15779733 | D7: =(1+C7)^G7 -> 1.2009936 | E7: =B7/D7 -> 300926.89 | F7: =F6+E7 -> -8562721.5 | G7: 1.25
A8: 40676 | B8: 361411.26 | C8: ='Get Rate for Iteration 6'!$B$4 -> 0.15779733 | D8: =(1+C8)^G8 -> 1.2458014 | E8: =B8/D8 -> 290103.43 | F8: =F7+E8 -> -8272618.1 | G8: 1.5
A9: 40768 | B9: 361411.26 | C9: ='Get Rate for Iteration 6'!$B$4 -> 0.15779733 | D9: =(1+C9)^G9 -> 1.292281 | E9: =B9/D9 -> 279669.26 | F9: =F8+E9 -> -7992948.8 | G9: 1.75
A10: 40860 | B10: 361411.26 | C10: ='Get Rate for Iteration 6'!$B$4 -> 0.15779733 | D10: =(1+C10)^G10 -> 1.3404947 | E10: =B10/D10 -> 269610.37 | F10: =F9+E10 -> -7723338.4 | G10: 2
A11: 40952 | B11: 361411.26 | C11: ='Get Rate for Iteration 6'!$B$4 -> 0.15779733 | D11: =(1+C11)^G11 -> 1.3905071 | E11: =B11/D11 -> 259913.27 | F11: =F10+E11 -> -7463425.2 | G11: 2.25
A12: 41042 | B12: 361411.26 | C12: ='Get Rate for Iteration 6'!$B$4 -> 0.15779733 | D12: =(1+C12)^G12 -> 1.4423855 | E12: =B12/D12 -> 250564.95 | F12: =F11+E12 -> -7212860.2 | G12: 2.5
A13: 41134 | B13: 361411.26 | C13: ='Get Rate for Iteration 6'!$B$4 -> 0.15779733 | D13: =(1+C13)^G13 -> 1.4961995 | E13: =B13/D13 -> 241552.86 | F13: =F12+E13 -> -6971307.4 | G13: 2.75
A14: 41226 | B14: 361411.26 | C14: ='Get Rate for Iteration 6'!$B$4 -> 0.15779733 | D14: =(1+C14)^G14 -> 1.5520211 | E14: =B14/D14 -> 232864.91 | F14: =F13+E14 -> -6738442.5 | G14: 3
... A30: 42687 | B30: 11481758 | C30: ='Get Rate for Iteration 6'!$B$4 -> 0.15779733 | D30: =(1+C30)^G30 -> 2.788867 | E30: =B30/D30 -> 4116997.2 | F30: =F29+E30 -> 17043.163 | G30: 7

Sheet Get Rate for Iteration 7 
A1: A3 = A2-y2*(a2-a1)/y2-y1
A4: A3 | B4: =B5-B7*(B5-B6)/(B7-B8) -> 0.15821289 | C4: New Rate
A5: a2 | B5: ='Iteration 6'!C2 -> 0.15779733 | C5: rate from iteration 6
A6: a1 | B6: ='Iteration 5 '!C2 -> 0.15286219 | C6: rate from iteration 5
A7: y2 | B7: ='Iteration 6'!F30 -> 17043.163 | C7: result from iteration 6
A8: y1 | B8: ='Iteration 5 '!F30 -> 219447.37 | C8: result from iteration 5

Sheet Iteration 7 
B1: Cash Flow | C1: Rate | D1: Rate ^ Interval | E1: IRR Function | F1: RF IRR Function | G1: Period Day Fraction
A2: 40130 | B2: -10183896 | C2: ='Get Rate for Iteration 7 '!$B$4 -> 0.15821289 | D2: =(1+C2)^G2 -> 1 | E2: =B2/D2 -> -10183896 | F2: =E2 -> -10183896 | G2: =1-1 -> 0
A3: 40222 | B3: 361411.26 | C3: ='Get Rate for Iteration 7 '!$B$4 -> 0.15821289 | D3: =(1+C3)^G3 -> 1.037402 | E3: =B3/D3 -> 348381.09 | F3: =F2+E3 -> -9835515.1 | G3: 0.25
A4: 40311 | B4: 361411.26 | C4: ='Get Rate for Iteration 7 '!$B$4 -> 0.15821289 | D4: =(1+C4)^G4 -> 1.076203 | E4: =B4/D4 -> 335820.71 | F4: =F3+E4 -> -9499694.4 | G4: 0.5
A5: 40403 | B5: 361411.26 | C5: ='Get Rate for Iteration 7 '!$B$4 -> 0.15821289 | D5: =(1+C5)^G5 -> 1.1164552 | E5: =B5/D5 -> 323713.18 | F5: =F4+E5 -> -9175981.2 | G5: 0.75
A6: 40495 | B6: 361411.26 | C6: ='Get Rate for Iteration 7 '!$B$4 -> 0.15821289 | D6: =(1+C6)^G6 -> 1.1582129 | E6: =B6/D6 -> 312042.17 | F6: =F5+E6 -> -8863939 | G6: 1
A7: 40587 | B7: 361411.26 | C7: ='Get Rate for Iteration 7 '!$B$4 -> 0.15821289 | D7: =(1+C7)^G7 -> 1.2015324 | E7: =B7/D7 -> 300791.93 | F7: =F6+E7 -> -8563147.1 | G7: 1.25
A8: 40676 | B8: 361411.26 | C8: ='Get Rate for Iteration 7 '!$B$4 -> 0.15821289 | D8: =(1+C8)^G8 -> 1.2464722 | E8: =B8/D8 -> 289947.31 | F8: =F7+E8 -> -8273199.8 | G8: 1.5
A9: 40768 | B9: 361411.26 | C9: ='Get Rate for Iteration 7 '!$B$4 -> 0.15821289 | D9: =(1+C9)^G9 -> 1.2930928 | E9: =B9/D9 -> 279493.68 | F9: =F8+E9 -> -7993706.1 | G9: 1.75
A10: 40860 | B10: 361411.26 | C10: ='Get Rate for Iteration 7 '!$B$4 -> 0.15821289 | D10: =(1+C10)^G10 -> 1.3414571 | E10: =B10/D10 -> 269416.94 | F10: =F9+E10 -> -7724289.2 | G10: 2
A11: 40952 | B11: 361411.26 | C11: ='Get Rate for Iteration 7 '!$B$4 -> 0.15821289 | D11: =(1+C11)^G11 -> 1.3916303 | E11: =B11/D11 -> 259703.5 | F11: =F10+E11 -> -7464585.7 | G11: 2.25
A12: 41042 | B12: 361411.26 | C12: ='Get Rate for Iteration 7 '!$B$4 -> 0.15821289 | D12: =(1+C12)^G12 -> 1.4436801 | E12: =B12/D12 -> 250340.26 | F12: =F11+E12 -> -7214245.4 | G12: 2.5
A13: 41134 | B13: 361411.26 | C13: ='Get Rate for Iteration 7 '!$B$4 -> 0.15821289 | D13: =(1+C13)^G13 -> 1.4976767 | E13: =B13/D13 -> 241314.6 | F13: =F12+E13 -> -6972930.8 | G13: 2.75
A14: 41226 | B14: 361411.26 | C14: ='Get Rate for Iteration 7 '!$B$4 -> 0.15821289 | D14: =(1+C14)^G14 -> 1.5536929 | E14: =B14/D14 -> 232614.35 | F14: =F13+E14 -> -6740316.5 | G14: 3
... A30: 42687 | B30: 11481758 | C30: ='Get Rate for Iteration 7 '!$B$4 -> 0.15821289 | D30: =(1+C30)^G30 -> 2.7958814 | E30: =B30/D30 -> 4106668.3 | F30: =F29+E30 -> 271.29869 | G30: 7

Sheet Get Rate for Iteration 8 
A1: A3 = A2-y2*(a2-a1)/y2-y1
A4: A3 | B4: =B5-B7*(B5-B6)/(B7-B8) -> 0.15821961 | C4: New Rate
A5: a2 | B5: ='Iteration 7 '!C2 -> 0.15821289 | C5: rate from iteration 7
A6: a1 | B6: ='Iteration 6'!C2 -> 0.15779733 | C6: rate from iteration 6
A7: y2 | B7: ='Iteration 7 '!F30 -> 271.29869 | C7: result from iteration 7
A8: y1 | B8: ='Iteration 6'!F30 -> 17043.163 | C8: result from iteration 6

Sheet Iteration 8 
B1: Cash Flow | C1: Rate | D1: Rate ^ Interval | E1: IRR Function | F1: RF IRR Function | G1: Period Day Fraction
A2: 40130 | B2: -10183896 | C2: ='Get Rate for Iteration 8 '!$B$4 -> 0.15821961 | D2: =(1+C2)^G2 -> 1 | E2: =B2/D2 -> -10183896 | F2: =E2 -> -10183896 | G2: =1-1 -> 0
A3: 40222 | B3: 361411.26 | C3: ='Get Rate for Iteration 8 '!$B$4 -> 0.15821961 | D3: =(1+C3)^G3 -> 1.0374035 | E3: =B3/D3 -> 348380.59 | F3: =F2+E3 -> -9835515.6 | G3: 0.25
A4: 40311 | B4: 361411.26 | C4: ='Get Rate for Iteration 8 '!$B$4 -> 0.15821961 | D4: =(1+C4)^G4 -> 1.0762061 | E4: =B4/D4 -> 335819.74 | F4: =F3+E4 -> -9499695.9 | G4: 0.5
A5: 40403 | B5: 361411.26 | C5: ='Get Rate for Iteration 8 '!$B$4 -> 0.15821961 | D5: =(1+C5)^G5 -> 1.11646 | E5: =B5/D5 -> 323711.77 | F5: =F4+E5 -> -9175984.1 | G5: 0.75
A6: 40495 | B6: 361411.26 | C6: ='Get Rate for Iteration 8 '!$B$4 -> 0.15821961 | D6: =(1+C6)^G6 -> 1.1582196 | E6: =B6/D6 -> 312040.36 | F6: =F5+E6 -> -8863943.7 | G6: 1
A7: 40587 | B7: 361411.26 | C7: ='Get Rate for Iteration 8 '!$B$4 -> 0.15821961 | D7: =(1+C7)^G7 -> 1.2015411 | E7: =B7/D7 -> 300789.75 | F7: =F6+E7 -> -8563154 | G7: 1.25
A8: 40676 | B8: 361411.26 | C8: ='Get Rate for Iteration 8 '!$B$4 -> 0.15821961 | D8: =(1+C8)^G8 -> 1.246483 | E8: =B8/D8 -> 289944.79 | F8: =F7+E8 -> -8273209.2 | G8: 1.5
A9: 40768 | B9: 361411.26 | C9: ='Get Rate for Iteration 8 '!$B$4 -> 0.15821961 | D9: =(1+C9)^G9 -> 1.2931059 | E9: =B9/D9 -> 279490.84 | F9: =F8+E9 -> -7993718.4 | G9: 1.75
A10: 40860 | B10: 361411.26 | C10: ='Get Rate for Iteration 8 '!$B$4 -> 0.15821961 | D10: =(1+C10)^G10 -> 1.3414727 | E10: =B10/D10 -> 269413.81 | F10: =F9+E10 -> -7724304.5 | G10: 2
A11: 40952 | B11: 361411.26 | C11: ='Get Rate for Iteration 8 '!$B$4 -> 0.15821961 | D11: =(1+C11)^G11 -> 1.3916485 | E11: =B11/D11 -> 259700.1 | F11: =F10+E11 -> -7464604.4 | G11: 2.25
A12: 41042 | B12: 361411.26 | C12: ='Get Rate for Iteration 8 '!$B$4 -> 0.15821961 | D12: =(1+C12)^G12 -> 1.4437011 | E12: =B12/D12 -> 250336.63 | F12: =F11+E12 -> -7214267.8 | G12: 2.5 | I12: FAIL
A13: 41134 | B13: 361411.26 | C13: ='Get Rate for Iteration 8 '!$B$4 -> 0.15821961 | D13: =(1+C13)^G13 -> 1.4977006 | E13: =B13/D13 -> 241310.75 | F13: =F12+E13 -> -6972957.1 | G13: 2.75
A14: 41226 | B14: 361411.26 | C14: ='Get Rate for Iteration 8 '!$B$4 -> 0.15821961 | D14: =(1+C14)^G14 -> 1.5537199 | E14: =B14/D14 -> 232610.3 | F14: =F13+E14 -> -6740346.8 | G14: 3
A15: 41318 | B15: 361411.26 | C15: ='Get Rate for Iteration 8 '!$B$4 -> 0.15821961 | D15: =(1+C15)^G15 -> 1.6118346 | E15: =B15/D15 -> 224223.54 | F15: =F14+E15 -> -6516123.2 | G15: 3.25
A16: 41407 | B16: 361411.26 | C16: ='Get Rate for Iteration 8 '!$B$4 -> 0.15821961 | D16: =(1+C16)^G16 -> 1.6721229 | E16: =B16/D16 -> 216139.17 | F16: =F15+E16 -> -6299984.1 | G16: 3.5
A17: 41499 | B17: 361411.26 | C17: ='Get Rate for Iteration 8 '!$B$4 -> 0.15821961 | D17: =(1+C17)^G17 -> 1.7346662 | E17: =B17/D17 -> 208346.28 | F17: =F16+E17 -> -6091637.8 | G17: 3.75
A18: 41591 | B18: 361411.26 | C18: ='Get Rate for Iteration 8 '!$B$4 -> 0.15821961 | D18: =(1+C18)^G18 -> 1.7995489 | E18: =B18/D18 -> 200834.36 | F18: =F17+E18 -> -5890803.4 | G18: 4
A19: 41683 | B19: 361411.26 | C19: ='Get Rate for Iteration 8 '!$B$4 -> 0.15821961 | D19: =(1+C19)^G19 -> 1.8668584 | E19: =B19/D19 -> 193593.29 | F19: =F18+E19 -> -5697210.1 | G19: 4.25
A20: 41772 | B20: 361411.26 | C20: ='Get Rate for Iteration 8 '!$B$4 -> 0.15821961 | D20: =(1+C20)^G20 -> 1.9366855 | E20: =B20/D20 -> 186613.29 | F20: =F19+E20 -> -5510596.8 | G20: 4.5
A21: 41864 | B21: 361411.26 | C21: ='Get Rate for Iteration 8 '!$B$4 -> 0.15821961 | D21: =(1+C21)^G21 -> 2.0091244 | E21: =B21/D21 -> 179884.95 | F21: =F20+E21 -> -5330711.9 | G21: 4.75
A22: 41956 | B22: 361411.26 | C22: ='Get Rate for Iteration 8 '!$B$4 -> 0.15821961 | D22: =(1+C22)^G22 -> 2.0842728 | E22: =B22/D22 -> 173399.21 | F22: =F21+E22 -> -5157312.7 | G22: 5
A23: 42048 | B23: 361411.26 | C23: ='Get Rate for Iteration 8 '!$B$4 -> 0.15821961 | D23: =(1+C23)^G23 -> 2.162232 | E23: =B23/D23 -> 167147.31 | F23: =F22+E23 -> -4990165.4 | G23: 5.25
A24: 42137 | B24: 361411.26 | C24: ='Get Rate for Iteration 8 '!$B$4 -> 0.15821961 | D24: =(1+C24)^G24 -> 2.2431072 | E24: =B24/D24 -> 161120.82 | F24: =F23+E24 -> -4829044.5 | G24: 5.5
... A30: 42687 | B30: 11481758 | C30: ='Get Rate for Iteration 8 '!$B$4 -> 0.15821961 | D30: =(1+C30)^G30 -> 2.795995 | E30: =B30/D30 -> 4106501.5 | F30: =F29+E30 -> 0.34189024 | G30: 7

Sheet Get Rate for Iteration 9 
A1: A3 = A2-y2*(a2-a1)/y2-y1
A4: A3 | B4: =B5-B7*(B5-B6)/(B7-B8) -> 0.15821962 | C4: New Rate
A5: a2 | B5: ='Iteration 8 '!C2 -> 0.15821961 | C5: rate from iteration 8
A6: a1 | B6: ='Iteration 7 '!C2 -> 0.15821289 | C6: rate from iteration 7
A7: y2 | B7: ='Iteration 8 '!F30 -> 0.34189024 | C7: result from iteration 8
A8: y1 | B8: ='Iteration 7 '!F30 -> 271.29869 | C8: result from iteration 7

Sheet Iteration 9 
B1: Cash Flow | C1: Rate | D1: Rate ^ Interval | E1: IRR Function | F1: RF IRR Function | G1: Period Day count
A2: 40130 | B2: -10183896 | C2: ='Get Rate for Iteration 9 '!$B$4 -> 0.15821962 | D2: =(1+C2)^G2 -> 1 | E2: =B2/D2 -> -10183896 | F2: =E2 -> -10183896 | G2: =1-1 -> 0
A3: 40222 | B3: 361411.26 | C3: ='Get Rate for Iteration 9 '!$B$4 -> 0.15821962 | D3: =(1+C3)^G3 -> 1.0374035 | E3: =B3/D3 -> 348380.59 | F3: =F2+E3 -> -9835515.6 | G3: 0.25
A4: 40311 | B4: 361411.26 | C4: ='Get Rate for Iteration 9 '!$B$4 -> 0.15821962 | D4: =(1+C4)^G4 -> 1.0762061 | E4: =B4/D4 -> 335819.74 | F4: =F3+E4 -> -9499695.9 | G4: 0.5
A5: 40403 | B5: 361411.26 | C5: ='Get Rate for Iteration 9 '!$B$4 -> 0.15821962 | D5: =(1+C5)^G5 -> 1.11646 | E5: =B5/D5 -> 323711.77 | F5: =F4+E5 -> -9175984.1 | G5: 0.75
A6: 40495 | B6: 361411.26 | C6: ='Get Rate for Iteration 9 '!$B$4 -> 0.15821962 | D6: =(1+C6)^G6 -> 1.1582196 | E6: =B6/D6 -> 312040.35 | F6: =F5+E6 -> -8863943.7 | G6: 1
A7: 40587 | B7: 361411.26 | C7: ='Get Rate for Iteration 9 '!$B$4 -> 0.15821962 | D7: =(1+C7)^G7 -> 1.2015411 | E7: =B7/D7 -> 300789.75 | F7: =F6+E7 -> -8563154 | G7: 1.25
A8: 40676 | B8: 361411.26 | C8: ='Get Rate for Iteration 9 '!$B$4 -> 0.15821962 | D8: =(1+C8)^G8 -> 1.246483 | E8: =B8/D8 -> 289944.79 | F8: =F7+E8 -> -8273209.2 | G8: 1.5
A9: 40768 | B9: 361411.26 | C9: ='Get Rate for Iteration 9 '!$B$4 -> 0.15821962 | D9: =(1+C9)^G9 -> 1.2931059 | E9: =B9/D9 -> 279490.84 | F9: =F8+E9 -> -7993718.4 | G9: 1.75
A10: 40860 | B10: 361411.26 | C10: ='Get Rate for Iteration 9 '!$B$4 -> 0.15821962 | D10: =(1+C10)^G10 -> 1.3414727 | E10: =B10/D10 -> 269413.81 | F10: =F9+E10 -> -7724304.6 | G10: 2
A11: 40952 | B11: 361411.26 | C11: ='Get Rate for Iteration 9 '!$B$4 -> 0.15821962 | D11: =(1+C11)^G11 -> 1.3916485 | E11: =B11/D11 -> 259700.1 | F11: =F10+E11 -> -7464604.5 | G11: 2.25 | I11: PASS
A12: 41042 | B12: 361411.26 | C12: ='Get Rate for Iteration 9 '!$B$4 -> 0.15821962 | D12: =(1+C12)^G12 -> 1.4437011 | E12: =B12/D12 -> 250336.62 | F12: =F11+E12 -> -7214267.8 | G12: 2.5
A13: 41134 | B13: 361411.26 | C13: ='Get Rate for Iteration 9 '!$B$4 -> 0.15821962 | D13: =(1+C13)^G13 -> 1.4977007 | E13: =B13/D13 -> 241310.74 | F13: =F12+E13 -> -6972957.1 | G13: 2.75
A14: 41226 | B14: 361411.26 | C14: ='Get Rate for Iteration 9 '!$B$4 -> 0.15821962 | D14: =(1+C14)^G14 -> 1.55372 | E14: =B14/D14 -> 232610.29 | F14: =F13+E14 -> -6740346.8 | G14: 3
A15: 41318 | B15: 361411.26 | C15: ='Get Rate for Iteration 9 '!$B$4 -> 0.15821962 | D15: =(1+C15)^G15 -> 1.6118346 | E15: =B15/D15 -> 224223.54 | F15: =F14+E15 -> -6516123.3 | G15: 3.25
A16: 41407 | B16: 361411.26 | C16: ='Get Rate for Iteration 9 '!$B$4 -> 0.15821962 | D16: =(1+C16)^G16 -> 1.6721229 | E16: =B16/D16 -> 216139.17 | F16: =F15+E16 -> -6299984.1 | G16: 3.5
A17: 41499 | B17: 361411.26 | C17: ='Get Rate for Iteration 9 '!$B$4 -> 0.15821962 | D17: =(1+C17)^G17 -> 1.7346663 | E17: =B17/D17 -> 208346.28 | F17: =F16+E17 -> -6091637.8 | G17: 3.75
A18: 41591 | B18: 361411.26 | C18: ='Get Rate for Iteration 9 '!$B$4 -> 0.15821962 | D18: =(1+C18)^G18 -> 1.7995489 | E18: =B18/D18 -> 200834.36 | F18: =F17+E18 -> -5890803.5 | G18: 4
A19: 41683 | B19: 361411.26 | C19: ='Get Rate for Iteration 9 '!$B$4 -> 0.15821962 | D19: =(1+C19)^G19 -> 1.8668585 | E19: =B19/D19 -> 193593.28 | F19: =F18+E19 -> -5697210.2 | G19: 4.25
A20: 41772 | B20: 361411.26 | C20: ='Get Rate for Iteration 9 '!$B$4 -> 0.15821962 | D20: =(1+C20)^G20 -> 1.9366856 | E20: =B20/D20 -> 186613.28 | F20: =F19+E20 -> -5510596.9 | G20: 4.5
A21: 41864 | B21: 361411.26 | C21: ='Get Rate for Iteration 9 '!$B$4 -> 0.15821962 | D21: =(1+C21)^G21 -> 2.0091245 | E21: =B21/D21 -> 179884.95 | F21: =F20+E21 -> -5330712 | G21: 4.75
A22: 41956 | B22: 361411.26 | C22: ='Get Rate for Iteration 9 '!$B$4 -> 0.15821962 | D22: =(1+C22)^G22 -> 2.0842729 | E22: =B22/D22 -> 173399.2 | F22: =F21+E22 -> -5157312.8 | G22: 5
A23: 42048 | B23: 361411.26 | C23: ='Get Rate for Iteration 9 '!$B$4 -> 0.15821962 | D23: =(1+C23)^G23 -> 2.1622321 | E23: =B23/D23 -> 167147.3 | F23: =F22+E23 -> -4990165.5 | G23: 5.25
... A30: 42687 | B30: 11481758 | C30: ='Get Rate for Iteration 9 '!$B$4 -> 0.15821962 | D30: =(1+C30)^G30 -> 2.7959951 | E30: =B30/D30 -> 4106501.3 | F30: =F29+E30 -> 6.8689696e-06 | G30: 7
