Workbook

Sheet Terms 
A1: Settlement | B1: 39251 | D1: Cost | E1: 13500000
A2: Maturity | B2: 41443 | D2: Face Value | E2: 12800000
A3: Rate | B3: 0.115 | D3: Discount | E3: =E2-E1 -> -700000
A4: Price | B4: =+E1/E2*100 -> 105.46875
A5: Redemption | B5: 100
A6: Coupon Frequency | B6: 1
A7: Day Basis | B7: 0
A8: Yield | B8: =YIELD(B1,B2,B3,B4,B5,B6,B7) -> 0.10235651

Sheet Iteration 1
A1: Date | B1: Cash Flow | C1: Face Value | D1: Coupon Rate | E1: Cash Payment | F1: Discount Rate | G1: Disc Amortization | H1: Carry Value
A2: 39251 | B2: -13500000 | C2: 12800000 | D2: 0.115 | F2: 0 | H2: =+B2*-1 -> 13500000
A3: 39617 | B3: =+D2*$C$2 -> 1472000 | C3: 12800000 | D3: 0.115 | E3: =+D3*C3 -> 1472000 | F3: 0 | G3: =E3-((H2*0.25*F3)) -> 1472000 | H3: =+H2-G3 -> 12028000
A4: 39982 | B4: =+D3*$C$2 -> 1472000 | C4: 12800000 | D4: 0.115 | E4: =+D4*C4 -> 1472000 | F4: 0 | G4: =E4-((H3*0.25*F4)) -> 1472000 | H4: =+H3-G4 -> 10556000
A5: 40347 | B5: =+D4*$C$2 -> 1472000 | C5: 12800000 | D5: 0.115 | E5: =+D5*C5 -> 1472000 | F5: 0 | G5: =E5-((H4*0.25*F5)) -> 1472000 | H5: =+H4-G5 -> 9084000
A6: 40712 | B6: =+D5*$C$2 -> 1472000 | C6: 12800000 | D6: 0.115 | E6: =+D6*C6 -> 1472000 | F6: 0 | G6: =E6-((H5*0.25*F6)) -> 1472000 | H6: =+H5-G6 -> 7612000
A7: 41078 | B7: =+D6*$C$2 -> 1472000 | C7: 12800000 | D7: 0.115 | E7: =+D7*C7 -> 1472000 | F7: 0 | G7: =E7-((H6*0.25*F7)) -> 1472000 | H7: =+H6-G7 -> 6140000
A8: 41443 | B8: =+D7*$C$2 -> 1472000 | C8: 12800000 | D8: 0.115 | E8: =+D8*C8 -> 1472000 | F8: 0 | G8: =E8-((H7*0.25*F8)) -> 1472000 | H8: =+H7-G8 -> 4668000
F34: XIRR Function | G34: =H8-C2 -> -8132000
F36: Tolerance | G36: 0.01

Sheet Iteration 2
A1: Date | B1: Cash Flow | C1: Face Value | D1: Coupon Rate | E1: Cash Payment | F1: Discount Rate | G1: Disc Amortization | H1: Carry Value
A2: 39251 | B2: -13500000 | C2: 12800000 | D2: 0.115 | F2: 0.0125 | H2: =+B2*-1 -> 13500000
A3: 39617 | B3: =+D2*$C$2 -> 1472000 | C3: 12800000 | D3: 0.115 | E3: =+D3*C3 -> 1472000 | F3: 0.0125 | G3: =E3-((H2*0.25*F3)) -> 1429812.5 | H3: =+H2-G3 -> 12070188
A4: 39982 | B4: =+D3*$C$2 -> 1472000 | C4: 12800000 | D4: 0.115 | E4: =+D4*C4 -> 1472000 | F4: 0.0125 | G4: =E4-((H3*0.25*F4)) -> 1434280.7 | H4: =+H3-G4 -> 10635907
A5: 40347 | B5: =+D4*$C$2 -> 1472000 | C5: 12800000 | D5: 0.115 | E5: =+D5*C5 -> 1472000 | F5: 0.0125 | G5: =E5-((H4*0.25*F5)) -> 1438762.8 | H5: =+H4-G5 -> 9197144
A6: 40712 | B6: =+D5*$C$2 -> 1472000 | C6: 12800000 | D6: 0.115 | E6: =+D6*C6 -> 1472000 | F6: 0.0125 | G6: =E6-((H5*0.25*F6)) -> 1443258.9 | H6: =+H5-G6 -> 7753885.1
A7: 41078 | B7: =+D6*$C$2 -> 1472000 | C7: 12800000 | D7: 0.115 | E7: =+D7*C7 -> 1472000 | F7: 0.0125 | G7: =E7-((H6*0.25*F7)) -> 1447769.1 | H7: =+H6-G7 -> 6306116
A8: 41443 | B8: =+D7*$C$2 -> 1472000 | C8: 12800000 | D8: 0.115 | E8: =+D8*C8 -> 1472000 | F8: 0.0125 | G8: =E8-((H7*0.25*F8)) -> 1452293.4 | H8: =+H7-G8 -> 4853822.6
F34: XIRR Function | G34: =H8-C2 -> -7946177.4
F36: Tolerance | G36: 0.01

Sheet Iteration 3
A1: Date | B1: Cash Flow | C1: Face Value | D1: Coupon Rate | E1: Cash Payment | F1: Discount Rate | G1: Disc Amortization | H1: Carry Value
A2: 39251 | B2: -13500000 | C2: 12800000 | D2: 0.115 | F2: 0.0875 | H2: =+B2*-1 -> 13500000
A3: 39617 | B3: =+D2*$C$2 -> 1472000 | C3: 12800000 | D3: 0.115 | E3: =+D3*C3 -> 1472000 | F3: 0.0875 | G3: =E3-((H2*0.25*F3)) -> 1176687.5 | H3: =+H2-G3 -> 12323312
A4: 39982 | B4: =+D3*$C$2 -> 1472000 | C4: 12800000 | D4: 0.115 | E4: =+D4*C4 -> 1472000 | F4: 0.0875 | G4: =E4-((H3*0.25*F4)) -> 1202427.5 | H4: =+H3-G4 -> 11120885
A5: 40347 | B5: =+D4*$C$2 -> 1472000 | C5: 12800000 | D5: 0.115 | E5: =+D5*C5 -> 1472000 | F5: 0.0875 | G5: =E5-((H4*0.25*F5)) -> 1228730.6 | H5: =+H4-G5 -> 9892154.3
A6: 40712 | B6: =+D5*$C$2 -> 1472000 | C6: 12800000 | D6: 0.115 | E6: =+D6*C6 -> 1472000 | F6: 0.0875 | G6: =E6-((H5*0.25*F6)) -> 1255609.1 | H6: =+H5-G6 -> 8636545.2
A7: 41078 | B7: =+D6*$C$2 -> 1472000 | C7: 12800000 | D7: 0.115 | E7: =+D7*C7 -> 1472000 | F7: 0.0875 | G7: =E7-((H6*0.25*F7)) -> 1283075.6 | H7: =+H6-G7 -> 7353469.6
A8: 41443 | B8: =+D7*$C$2 -> 1472000 | C8: 12800000 | D8: 0.115 | E8: =+D8*C8 -> 1472000 | F8: 0.0875 | G8: =E8-((H7*0.25*F8)) -> 1311142.9 | H8: =+H7-G8 -> 6042326.8
F34: XIRR Function | G34: =H8-C2 -> -6757673.2
F36: Tolerance | G36: 0.01

Sheet Get Rate for Iteration 4
A1: A3 = A2-y2*(a2-a1)/y2-y1
A4: A3 | B4: =B5-B7*(B5-B6)/(B7-B8) -> 0.51393982 | C4: New Rate
A5: a2 | B5: 0.0875 | C5: Rate from Iteration 2
A6: a1 | B6: 0.0125 | C6: Rate from Iteration 1
A7: y2 | B7: ='Iteration 3'!G34 -> -6757673.2 | C7: Result from Iteration 2
A8: y1 | B8: ='Iteration 2'!G34 -> -7946177.4 | C8: Result from Iteration1

Sheet Iteration 4 
A1: Date | B1: Cash Flow | C1: Face Value | D1: Coupon Rate | E1: Cash Payment | F1: Discount Rate | G1: Disc Amortization | H1: Carry Value
A2: 39251 | B2: -13500000 | C2: 12800000 | D2: 0.115 | F2: ='Get Rate for Iteration 4'!$B$4 -> 0.51393982 | H2: =+B2*-1 -> 13500000
A3: 39617 | B3: =+D2*$C$2 -> 1472000 | C3: 12800000 | D3: 0.115 | E3: =+D3*C3 -> 1472000 | F3: ='Get Rate for Iteration 4'!$B$4 -> 0.51393982 | G3: =E3-((H2*0.25*F3)) -> -262546.89 | H3: =+H2-G3 -> 13762547
A4: 39982 | B4: =+D3*$C$2 -> 1472000 | C4: 12800000 | D4: 0.115 | E4: =+D4*C4 -> 1472000 | F4: ='Get Rate for Iteration 4'!$B$4 -> 0.51393982 | G4: =E4-((H3*0.25*F4)) -> -296280.21 | H4: =+H3-G4 -> 14058827
A5: 40347 | B5: =+D4*$C$2 -> 1472000 | C5: 12800000 | D5: 0.115 | E5: =+D5*C5 -> 1472000 | F5: ='Get Rate for Iteration 4'!$B$4 -> 0.51393982 | G5: =E5-((H4*0.25*F5)) -> -334347.76 | H5: =+H4-G5 -> 14393175
A6: 40712 | B6: =+D5*$C$2 -> 1472000 | C6: 12800000 | D6: 0.115 | E6: =+D6*C6 -> 1472000 | F6: ='Get Rate for Iteration 4'!$B$4 -> 0.51393982 | G6: =E6-((H5*0.25*F6)) -> -377306.42 | H6: =+H5-G6 -> 14770481
A7: 41078 | B7: =+D6*$C$2 -> 1472000 | C7: 12800000 | D7: 0.115 | E7: =+D7*C7 -> 1472000 | F7: ='Get Rate for Iteration 4'!$B$4 -> 0.51393982 | G7: =E7-((H6*0.25*F7)) -> -425784.62 | H7: =+H6-G7 -> 15196266
A8: 41443 | B8: =+D7*$C$2 -> 1472000 | C8: 12800000 | D8: 0.115 | E8: =+D8*C8 -> 1472000 | F8: ='Get Rate for Iteration 4'!$B$4 -> 0.51393982 | G8: =E8-((H7*0.25*F8)) -> -480491.53 | H8: =+H7-G8 -> 15676757
F34: XIRR Function | G34: =H8-C2 -> 2876757.4
F36: Tolerance | G36: 0.01

Sheet Get Rate for Iteration 5
A1: A3 = A2-y2*(a2-a1)/y2-y1
A4: A3 | B4: =B5-B7*(B5-B6)/(B7-B8) -> 0.38660859 | C4: New Rate
A5: a2 | B5: ='Iteration 4 '!F2 -> 0.51393982 | C5: Rate from Iteration 2
A6: a1 | B6: ='Iteration 3'!F2 -> 0.0875 | C6: Rate from Iteration 1
A7: y2 | B7: ='Iteration 4 '!G34 -> 2876757.4 | C7: Result from Iteration 2
A8: y1 | B8: ='Iteration 3'!G34 -> -6757673.2 | C8: Result from Iteration1

Sheet Iteration 5
A1: Date | B1: Cash Flow | C1: Face Value | D1: Coupon Rate | E1: Cash Payment | F1: Discount Rate | G1: Disc Amortization | H1: Carry Value
A2: 39251 | B2: -13500000 | C2: 12800000 | D2: 0.115 | F2: ='Get Rate for Iteration 5'!$B$4 -> 0.38660859 | H2: =+B2*-1 -> 13500000
A3: 39617 | B3: =+D2*$C$2 -> 1472000 | C3: 12800000 | D3: 0.115 | E3: =+D3*C3 -> 1472000 | F3: ='Get Rate for Iteration 5'!$B$4 -> 0.38660859 | G3: =E3-((H2*0.25*F3)) -> 167196.02 | H3: =+H2-G3 -> 13332804
A4: 39982 | B4: =+D3*$C$2 -> 1472000 | C4: 12800000 | D4: 0.115 | E4: =+D4*C4 -> 1472000 | F4: ='Get Rate for Iteration 5'!$B$4 -> 0.38660859 | G4: =E4-((H3*0.25*F4)) -> 183355.87 | H4: =+H3-G4 -> 13149448
A5: 40347 | B5: =+D4*$C$2 -> 1472000 | C5: 12800000 | D5: 0.115 | E5: =+D5*C5 -> 1472000 | F5: ='Get Rate for Iteration 5'!$B$4 -> 0.38660859 | G5: =E5-((H4*0.25*F5)) -> 201077.61 | H5: =+H4-G5 -> 12948371
A6: 40712 | B6: =+D5*$C$2 -> 1472000 | C6: 12800000 | D6: 0.115 | E6: =+D6*C6 -> 1472000 | F6: ='Get Rate for Iteration 5'!$B$4 -> 0.38660859 | G6: =E6-((H5*0.25*F6)) -> 220512.19 | H6: =+H5-G6 -> 12727858
A7: 41078 | B7: =+D6*$C$2 -> 1472000 | C7: 12800000 | D7: 0.115 | E7: =+D7*C7 -> 1472000 | F7: ='Get Rate for Iteration 5'!$B$4 -> 0.38660859 | G7: =E7-((H6*0.25*F7)) -> 241825.17 | H7: =+H6-G7 -> 12486033
A8: 41443 | B8: =+D7*$C$2 -> 1472000 | C8: 12800000 | D8: 0.115 | E8: =+D8*C8 -> 1472000 | F8: ='Get Rate for Iteration 5'!$B$4 -> 0.38660859 | G8: =E8-((H7*0.25*F8)) -> 265198.09 | H8: =+H7-G8 -> 12220835
F34: XIRR Function | G34: =H8-C2 -> -579164.95
F36: Tolerance | G36: 0.01

Sheet Get Rate for Iteration 6
A1: A3 = A2-y2*(a2-a1)/y2-y1
A4: A3 | B4: =B5-B7*(B5-B6)/(B7-B8) -> 0.40794755 | C4: New Rate
A5: a2 | B5: ='Iteration 5'!F2 -> 0.38660859 | C5: Rate from Iteration 2
A6: a1 | B6: ='Iteration 4 '!F2 -> 0.51393982 | C6: Rate from Iteration 1
A7: y2 | B7: ='Iteration 5'!G34 -> -579164.95 | C7: Result from Iteration 2
A8: y1 | B8: ='Iteration 4 '!G34 -> 2876757.4 | C8: Result from Iteration1

Sheet Iteration 6
A1: Date | B1: Cash Flow | C1: Face Value | D1: Coupon Rate | E1: Cash Payment | F1: Discount Rate | G1: Disc Amortization | H1: Carry Value
A2: 39251 | B2: -13500000 | C2: 12800000 | D2: 0.115 | F2: ='Get Rate for Iteration 6'!$B$4 -> 0.40794755 | H2: =+B2*-1 -> 13500000
A3: 39617 | B3: =+D2*$C$2 -> 1472000 | C3: 12800000 | D3: 0.115 | E3: =+D3*C3 -> 1472000 | F3: ='Get Rate for Iteration 6'!$B$4 -> 0.40794755 | G3: =E3-((H2*0.25*F3)) -> 95177.03 | H3: =+H2-G3 -> 13404823
A4: 39982 | B4: =+D3*$C$2 -> 1472000 | C4: 12800000 | D4: 0.115 | E4: =+D4*C4 -> 1472000 | F4: ='Get Rate for Iteration 6'!$B$4 -> 0.40794755 | G4: =E4-((H3*0.25*F4)) -> 104883.84 | H4: =+H3-G4 -> 13299939
A5: 40347 | B5: =+D4*$C$2 -> 1472000 | C5: 12800000 | D5: 0.115 | E5: =+D5*C5 -> 1472000 | F5: ='Get Rate for Iteration 6'!$B$4 -> 0.40794755 | G5: =E5-((H4*0.25*F5)) -> 115580.62 | H5: =+H4-G5 -> 13184359
A6: 40712 | B6: =+D5*$C$2 -> 1472000 | C6: 12800000 | D6: 0.115 | E6: =+D6*C6 -> 1472000 | F6: ='Get Rate for Iteration 6'!$B$4 -> 0.40794755 | G6: =E6-((H5*0.25*F6)) -> 127368.32 | H6: =+H5-G6 -> 13056990
A7: 41078 | B7: =+D6*$C$2 -> 1472000 | C7: 12800000 | D7: 0.115 | E7: =+D7*C7 -> 1472000 | F7: ='Get Rate for Iteration 6'!$B$4 -> 0.40794755 | G7: =E7-((H6*0.25*F7)) -> 140358.22 | H7: =+H6-G7 -> 12916632
A8: 41443 | B8: =+D7*$C$2 -> 1472000 | C8: 12800000 | D8: 0.115 | E8: =+D8*C8 -> 1472000 | F8: ='Get Rate for Iteration 6'!$B$4 -> 0.40794755 | G8: =E8-((H7*0.25*F8)) -> 154672.92 | H8: =+H7-G8 -> 12761959
F34: XIRR Function | G34: =H8-C2 -> -38040.95
F36: Tolerance | G36: 0.01

Sheet Get Rate for Iteration 7 
A1: A3 = A2-y2*(a2-a1)/y2-y1
A4: A3 | B4: =B5-B7*(B5-B6)/(B7-B8) -> 0.40944767 | C4: New Rate
A5: a2 | B5: ='Iteration 6'!F2 -> 0.40794755 | C5: Rate from Iteration 2
A6: a1 | B6: ='Iteration 5'!F2 -> 0.38660859 | C6: Rate from Iteration 1
A7: y2 | B7: ='Iteration 6'!G34 -> -38040.95 | C7: Result from Iteration 2
A8: y1 | B8: ='Iteration 5'!G34 -> -579164.95 | C8: Result from Iteration1

Sheet Iteration 7 
A1: Date | B1: Cash Flow | C1: Face Value | D1: Coupon Rate | E1: Cash Payment | F1: Discount Rate | G1: Disc Amortization | H1: Carry Value
A2: 39251 | B2: -13500000 | C2: 12800000 | D2: 0.115 | F2: ='Get Rate for Iteration 7 '!$B$4 -> 0.40944767 | H2: =+B2*-1 -> 13500000
A3: 39617 | B3: =+D2*$C$2 -> 1472000 | C3: 12800000 | D3: 0.115 | E3: =+D3*C3 -> 1472000 | F3: ='Get Rate for Iteration 7 '!$B$4 -> 0.40944767 | G3: =E3-((H2*0.25*F3)) -> 90114.105 | H3: =+H2-G3 -> 13409886
A4: 39982 | B4: =+D3*$C$2 -> 1472000 | C4: 12800000 | D4: 0.115 | E4: =+D4*C4 -> 1472000 | F4: ='Get Rate for Iteration 7 '!$B$4 -> 0.40944767 | G4: =E4-((H3*0.25*F4)) -> 99338.357 | H4: =+H3-G4 -> 13310548
A5: 40347 | B5: =+D4*$C$2 -> 1472000 | C5: 12800000 | D5: 0.115 | E5: =+D5*C5 -> 1472000 | F5: ='Get Rate for Iteration 7 '!$B$4 -> 0.40944767 | G5: =E5-((H4*0.25*F5)) -> 109506.82 | H5: =+H4-G5 -> 13201041
A6: 40712 | B6: =+D5*$C$2 -> 1472000 | C6: 12800000 | D6: 0.115 | E6: =+D6*C6 -> 1472000 | F6: ='Get Rate for Iteration 7 '!$B$4 -> 0.40944767 | G6: =E6-((H5*0.25*F6)) -> 120716.15 | H6: =+H5-G6 -> 13080325
A7: 41078 | B7: =+D6*$C$2 -> 1472000 | C7: 12800000 | D7: 0.115 | E7: =+D7*C7 -> 1472000 | F7: ='Get Rate for Iteration 7 '!$B$4 -> 0.40944767 | G7: =E7-((H6*0.25*F7)) -> 133072.89 | H7: =+H6-G7 -> 12947252
A8: 41443 | B8: =+D7*$C$2 -> 1472000 | C8: 12800000 | D8: 0.115 | E8: =+D8*C8 -> 1472000 | F8: ='Get Rate for Iteration 7 '!$B$4 -> 0.40944767 | G8: =E8-((H7*0.25*F8)) -> 146694.48 | H8: =+H7-G8 -> 12800557
F34: XIRR Function | G34: =H8-C2 -> 557.19513
F36: Tolerance | G36: 0.01

Sheet Get Rate for Iteration 8 
A1: A3 = A2-y2*(a2-a1)/y2-y1
A4: A3 | B4: =B5-B7*(B5-B6)/(B7-B8) -> 0.40942602 | C4: New Rate
A5: a2 | B5: ='Iteration 7 '!F2 -> 0.40944767 | C5: Rate from Iteration 2
A6: a1 | B6: ='Iteration 6'!F2 -> 0.40794755 | C6: Rate from Iteration 1
A7: y2 | B7: ='Iteration 7 '!G34 -> 557.19513 | C7: Result from Iteration 2
A8: y1 | B8: ='Iteration 6'!G34 -> -38040.95 | C8: Result from Iteration1

Sheet Iteration 8 
A1: Date | B1: Cash Flow | C1: Face Value | D1: Coupon Rate | E1: Cash Payment | F1: Discount Rate | G1: Disc Amortization | H1: Carry Value
A2: 39251 | B2: -13500000 | C2: 12800000 | D2: 0.115 | F2: ='Get Rate for Iteration 8 '!$B$4 -> 0.40942602 | H2: =+B2*-1 -> 13500000
A3: 39617 | B3: =+D2*$C$2 -> 1472000 | C3: 12800000 | D3: 0.115 | E3: =+D3*C3 -> 1472000 | F3: ='Get Rate for Iteration 8 '!$B$4 -> 0.40942602 | G3: =E3-((H2*0.25*F3)) -> 90187.192 | H3: =+H2-G3 -> 13409813
A4: 39982 | B4: =+D3*$C$2 -> 1472000 | C4: 12800000 | D4: 0.115 | E4: =+D4*C4 -> 1472000 | F4: ='Get Rate for Iteration 8 '!$B$4 -> 0.40942602 | G4: =E4-((H3*0.25*F4)) -> 99418.438 | H4: =+H3-G4 -> 13310394
A5: 40347 | B5: =+D4*$C$2 -> 1472000 | C5: 12800000 | D5: 0.115 | E5: =+D5*C5 -> 1472000 | F5: ='Get Rate for Iteration 8 '!$B$4 -> 0.40942602 | G5: =E5-((H4*0.25*F5)) -> 109594.56 | H5: =+H4-G5 -> 13200800
A6: 40712 | B6: =+D5*$C$2 -> 1472000 | C6: 12800000 | D6: 0.115 | E6: =+D6*C6 -> 1472000 | F6: ='Get Rate for Iteration 8 '!$B$4 -> 0.40942602 | G6: =E6-((H5*0.25*F6)) -> 120812.28 | H6: =+H5-G6 -> 13079988
A7: 41078 | B7: =+D6*$C$2 -> 1472000 | C7: 12800000 | D7: 0.115 | E7: =+D7*C7 -> 1472000 | F7: ='Get Rate for Iteration 8 '!$B$4 -> 0.40942602 | G7: =E7-((H6*0.25*F7)) -> 133178.2 | H7: =+H6-G7 -> 12946809
A8: 41443 | B8: =+D7*$C$2 -> 1472000 | C8: 12800000 | D8: 0.115 | E8: =+D8*C8 -> 1472000 | F8: ='Get Rate for Iteration 8 '!$B$4 -> 0.40942602 | G8: =E8-((H7*0.25*F8)) -> 146809.86 | H8: =+H7-G8 -> 12799999
F34: XIRR Function | G34: =H8-C2 -> -0.52451068
F36: Tolerance | G36: 0.01

Sheet Get Rate for Iteration 9 
A1: A3 = A2-y2*(a2-a1)/y2-y1
A4: A3 | B4: =B5-B7*(B5-B6)/(B7-B8) -> 0.40942604 | C4: New Rate
A5: a2 | B5: ='Iteration 8 '!F2 -> 0.40942602 | C5: Rate from Iteration 2
A6: a1 | B6: ='Iteration 7 '!F2 -> 0.40944767 | C6: Rate from Iteration 1
A7: y2 | B7: ='Iteration 8 '!G34 -> -0.52451068 | C7: Result from Iteration 2
A8: y1 | B8: ='Iteration 7 '!G34 -> 557.19513 | C8: Result from Iteration1

Sheet Iteration 9 
A1: Date | B1: Cash Flow | C1: Face Value | D1: Coupon Rate | E1: Cash Payment | F1: Discount Rate | G1: Disc Amortization | H1: Carry Value
A2: 39251 | B2: -13500000 | C2: 12800000 | D2: 0.115 | F2: ='Get Rate for Iteration 9 '!$B$4 -> 0.40942604 | H2: =+B2*-1 -> 13500000
A3: 39617 | B3: =+D2*$C$2 -> 1472000 | C3: 12800000 | D3: 0.115 | E3: =+D3*C3 -> 1472000 | F3: ='Get Rate for Iteration 9 '!$B$4 -> 0.40942604 | G3: =E3-((H2*0.25*F3)) -> 90187.123 | H3: =+H2-G3 -> 13409813
A4: 39982 | B4: =+D3*$C$2 -> 1472000 | C4: 12800000 | D4: 0.115 | E4: =+D4*C4 -> 1472000 | F4: ='Get Rate for Iteration 9 '!$B$4 -> 0.40942604 | G4: =E4-((H3*0.25*F4)) -> 99418.362 | H4: =+H3-G4 -> 13310395
A5: 40347 | B5: =+D4*$C$2 -> 1472000 | C5: 12800000 | D5: 0.115 | E5: =+D5*C5 -> 1472000 | F5: ='Get Rate for Iteration 9 '!$B$4 -> 0.40942604 | G5: =E5-((H4*0.25*F5)) -> 109594.48 | H5: =+H4-G5 -> 13200800
A6: 40712 | B6: =+D5*$C$2 -> 1472000 | C6: 12800000 | D6: 0.115 | E6: =+D6*C6 -> 1472000 | F6: ='Get Rate for Iteration 9 '!$B$4 -> 0.40942604 | G6: =E6-((H5*0.25*F6)) -> 120812.19 | H6: =+H5-G6 -> 13079988
A7: 41078 | B7: =+D6*$C$2 -> 1472000 | C7: 12800000 | D7: 0.115 | E7: =+D7*C7 -> 1472000 | F7: ='Get Rate for Iteration 9 '!$B$4 -> 0.40942604 | G7: =E7-((H6*0.25*F7)) -> 133178.1 | H7: =+H6-G7 -> 12946810
A8: 41443 | B8: =+D7*$C$2 -> 1472000 | C8: 12800000 | D8: 0.115 | E8: =+D8*C8 -> 1472000 | F8: ='Get Rate for Iteration 9 '!$B$4 -> 0.40942604 | G8: =E8-((H7*0.25*F8)) -> 146809.75 | H8: =+H7-G8 -> 12800000
F34: XIRR Function | G34: =H8-C2 -> -7.2214752e-06
F36: Tolerance | G36: 0.01

Sheet Get Rate for Iteration 10 
A1: A3 = A2-y2*(a2-a1)/y2-y1
A4: A3 | B4: =B5-B7*(B5-B6)/(B7-B8) -> 0.40942604 | C4: New Rate
A5: a2 | B5: ='Iteration 9 '!F2 -> 0.40942604 | C5: Rate from Iteration 2
A6: a1 | B6: ='Iteration 8 '!F2 -> 0.40942602 | C6: Rate from Iteration 1
A7: y2 | B7: ='Iteration 9 '!G34 -> -7.2214752e-06 | C7: Result from Iteration 2
A8: y1 | B8: ='Iteration 8 '!G34 -> -0.52451068 | C8: Result from Iteration1

Sheet Iteration 10 
A1: Date | B1: Cash Flow | C1: Face Value | D1: Coupon Rate | E1: Cash Payment | F1: Discount Rate | G1: Disc Amortization | H1: Carry Value
A2: 39251 | B2: -13500000 | C2: 12800000 | D2: 0.115 | F2: ='Get Rate for Iteration 10 '!$B$4 -> 0.40942604 | H2: =+B2*-1 -> 13500000
A3: 39617 | B3: =+D2*$C$2 -> 1472000 | C3: 12800000 | D3: 0.115 | E3: =+D3*C3 -> 1472000 | F3: ='Get Rate for Iteration 10 '!$B$4 -> 0.40942604 | G3: =E3-((H2*0.25*F3)) -> 90187.123 | H3: =+H2-G3 -> 13409813
A4: 39982 | B4: =+D3*$C$2 -> 1472000 | C4: 12800000 | D4: 0.115 | E4: =+D4*C4 -> 1472000 | F4: ='Get Rate for Iteration 10 '!$B$4 -> 0.40942604 | G4: =E4-((H3*0.25*F4)) -> 99418.362 | H4: =+H3-G4 -> 13310395
A5: 40347 | B5: =+D4*$C$2 -> 1472000 | C5: 12800000 | D5: 0.115 | E5: =+D5*C5 -> 1472000 | F5: ='Get Rate for Iteration 10 '!$B$4 -> 0.40942604 | G5: =E5-((H4*0.25*F5)) -> 109594.48 | H5: =+H4-G5 -> 13200800
A6: 40712 | B6: =+D5*$C$2 -> 1472000 | C6: 12800000 | D6: 0.115 | E6: =+D6*C6 -> 1472000 | F6: ='Get Rate for Iteration 10 '!$B$4 -> 0.40942604 | G6: =E6-((H5*0.25*F6)) -> 120812.19 | H6: =+H5-G6 -> 13079988
A7: 41078 | B7: =+D6*$C$2 -> 1472000 | C7: 12800000 | D7: 0.115 | E7: =+D7*C7 -> 1472000 | F7: ='Get Rate for Iteration 10 '!$B$4 -> 0.40942604 | G7: =E7-((H6*0.25*F7)) -> 133178.1 | H7: =+H6-G7 -> 12946810
A8: 41443 | B8: =+D7*$C$2 -> 1472000 | C8: 12800000 | D8: 0.115 | E8: =+D8*C8 -> 1472000 | F8: ='Get Rate for Iteration 10 '!$B$4 -> 0.40942604 | G8: =E8-((H7*0.25*F8)) -> 146809.75 | H8: =+H7-G8 -> 12800000
F34: XIRR Function | G34: =H8-C2 -> 0
F36: Tolerance | G36: 0.01

Sheet XIRR 
A1: Date | B1: Cash Flow | C1: XIRR
A2: 40130 | B2: -10183896 | C2: =XIRR(B2:B30,A2:A30) -> 0.15812421
A3: 40222 | B3: 361411.26
A4: 40311 | B4: 361411.26
A5: 40403 | B5: 361411.26
A6: 40495 | B6: 361411.26
A7: 40587 | B7: 361411.26
A8: 40676 | B8: 361411.26
A9: 40768 | B9: 361411.26
A10: 40860 | B10: 361411.26
A11: 40952 | B11: 361411.26
A12: 41042 | B12: 361411.26
A13: 41134 | B13: 361411.26
A14: 41226 | B14: 361411.26
... A30: 42687 | B30: 11481758

Sheet Carry Value Proof 
A1: Day Basis = 30/360 | E1: 0.15821962 | J1: Day Basis = 30/360 | N1: 0.14961419
A2: Date | B2: Cash Flow | C2: Face Value | D2: Carry Value | E2: Effective Interest Rate | F2: Disc Amortization | J2: Date | K2: Cash Flow | L2: Face Value | M2: Carry Value | N2: Effective Interest Rate | O2: Disc Amortization
A3: 40130 | B3: -10183896 | C3: 11120346 | D3: 10183896 | E3: =+E1 -> 0.15821962 | J3: 40130 | K3: -10183896 | L3: 11120346 | M3: 10183896 | N3: =+N1 -> 0.14961419
A4: 40222 | B4: 361411.26 | D4: =+D3+F4 -> 10225308 | F4: =(0.25*$E$3*D3)-B4 -> 41411.778 | J4: 40222 | K4: 361411.26 | M4: =+M3+O4 -> 10203399 | O4: =(0.25*$N$3*M3)-K4 -> 19502.592
A5: 40311 | B5: 361411.26 | D5: =+D4+F5 -> 10268358 | F5: =(0.25*$E$3*D4)-B5 -> 43049.817 | J5: 40311 | K5: 361411.26 | M5: =+M4+O5 -> 10223631 | O5: =(0.25*$N$3*M4)-K5 -> 20232.059
A6: 40403 | B6: 361411.26 | D6: =+D5+F6 -> 10313110 | F6: =(0.25*$E$3*D5)-B6 -> 44752.648 | J6: 40403 | K6: 361411.26 | M6: =+M5+O6 -> 10244620 | O6: =(0.25*$N$3*M5)-K6 -> 20988.809
A7: 40495 | B7: 361411.26 | D7: =+D6+F7 -> 10359633 | F7: =(0.25*$E$3*D6)-B7 -> 46522.835 | J7: 40495 | K7: 361411.26 | M7: =+M6+O7 -> 10266394 | O7: =(0.25*$N$3*M6)-K7 -> 21773.865
A8: 40587 | B8: 361411.26 | D8: =+D7+F8 -> 10407996 | F8: =(0.25*$E$3*D7)-B8 -> 48363.041 | J8: 40587 | K8: 361411.26 | M8: =+M7+O8 -> 10288982 | O8: =(0.25*$N$3*M7)-K8 -> 22588.285
A9: 40676 | B9: 361411.26 | D9: =+D8+F9 -> 10458272 | F9: =(0.25*$E$3*D8)-B9 -> 50276.037 | J9: 40676 | K9: 361411.26 | M9: =+M8+O9 -> 10312415 | O9: =(0.25*$N$3*M8)-K9 -> 23433.167
A10: 40768 | B10: 361411.26 | D10: =+D9+F10 -> 10510537 | F10: =(0.25*$E$3*D9)-B10 -> 52264.701 | J10: 40768 | K10: 361411.26 | M10: =+M9+O10 -> 10336725 | O10: =(0.25*$N$3*M9)-K10 -> 24309.651
A11: 40860 | B11: 361411.26 | D11: =+D10+F11 -> 10564869 | F11: =(0.25*$E$3*D10)-B11 -> 54332.026 | J11: 40860 | K11: 361411.26 | M11: =+M10+O11 -> 10361944 | O11: =(0.25*$N$3*M10)-K11 -> 25218.918
A12: 40952 | B12: 361411.26 | D12: =+D11+F12 -> 10621350 | F12: =(0.25*$E$3*D11)-B12 -> 56481.124 | J12: 40952 | K12: 361411.26 | M12: =+M11+O12 -> 10388106 | O12: =(0.25*$N$3*M11)-K12 -> 26162.195
A13: 41042 | B13: 361411.26 | D13: =+D12+F13 -> 10680065 | F13: =(0.25*$E$3*D12)-B13 -> 58715.229 | J13: 41042 | K13: 361411.26 | M13: =+M12+O13 -> 10415246 | O13: =(0.25*$N$3*M12)-K13 -> 27140.754
A14: 41134 | B14: 361411.26 | D14: =+D13+F14 -> 10741103 | F14: =(0.25*$E$3*D13)-B14 -> 61037.705 | J14: 41134 | K14: 361411.26 | M14: =+M13+O14 -> 10443402 | O14: =(0.25*$N$3*M13)-K14 -> 28155.914
A15: 41226 | B15: 361411.26 | D15: =+D14+F15 -> 10804555 | F15: =(0.25*$E$3*D14)-B15 -> 63452.045 | J15: 41226 | K15: 361411.26 | M15: =+M14+O15 -> 10472611 | O15: =(0.25*$N$3*M14)-K15 -> 29209.045
... A19: 41591 | B19: 361411.26 | D19: =+D18+F19 -> 11084474 | F19: =(0.25*$E$3*D18)-B19 -> 74102.925 | J19: 41591 | K19: 361411.26 | M19: =+M18+O19 -> 10600789 | O19: =(0.25*$N$3*M18)-K19 -> 33830.489
A20: 41683 | B20: 361411.26 | D20: =+D19+F20 -> 11161508 | F20: =(0.25*$E$3*D19)-B20 -> 77034.059 | G20: Discount Fully Amortized | J20: 41683 | K20: 361411.26 | M20: =+M19+O20 -> 10635885 | O20: =(0.25*$N$3*M19)-K20 -> 35095.87
A21: 41772 | B21: 361411.26 | D21: =+D20+F21 -> 11241590 | F21: =(0.25*$E$3*D20)-B21 -> 80081.134 | J21: 41772 | K21: 361411.26 | M21: =+M20+O21 -> 10672294 | O21: =(0.25*$N$3*M20)-K21 -> 36408.58
A22: 41864 | B22: 361411.26 | D22: =+D21+F22 -> 11324838 | F22: =(0.25*$E$3*D21)-B22 -> 83248.735 | J22: 41864 | K22: 361411.26 | M22: =+M21+O22 -> 10710064 | O22: =(0.25*$N$3*M21)-K22 -> 37770.39
A23: 41956 | B23: 361411.26 | D23: =+D22+F23 -> 11411380 | F23: =(0.25*$E$3*D22)-B23 -> 86541.631 | J23: 41956 | K23: 361411.26 | M23: =+M22+O23 -> 10749247 | O23: =(0.25*$N$3*M22)-K23 -> 39183.136
A24: 42048 | B24: 361411.26 | D24: =+D23+F24 -> 11501345 | F24: =(0.25*$E$3*D23)-B24 -> 89964.777 | J24: 42048 | K24: 361411.26 | M24: =+M23+O24 -> 10789896 | O24: =(0.25*$N$3*M23)-K24 -> 40648.725
A25: 42137 | B25: 361411.26 | D25: =+D24+F25 -> 11594868 | F25: =(0.25*$E$3*D24)-B25 -> 93523.325 | J25: 42137 | K25: 361411.26 | M25: =+M24+O25 -> 10832065 | O25: =(0.25*$N$3*M24)-K25 -> 42169.131
A26: 42229 | B26: 361411.26 | D26: =+D25+F26 -> 11692091 | F26: =(0.25*$E$3*D25)-B26 -> 97222.631 | J26: 42229 | K26: 361411.26 | M26: =+M25+O26 -> 10875811 | O26: =(0.25*$N$3*M25)-K26 -> 43746.406
A27: 42321 | B27: 361411.26 | D27: =+D26+F27 -> 11793159 | F27: =(0.25*$E$3*D26)-B27 -> 101068.26 | J27: 42321 | K27: 361411.26 | M27: =+M26+O27 -> 10921194 | O27: =(0.25*$N$3*M26)-K27 -> 45382.677
A28: 42413 | B28: 361411.26 | D28: =+D27+F28 -> 11898225 | F28: =(0.25*$E$3*D27)-B28 -> 105066.01 | J28: 42413 | K28: 361411.26 | M28: =+M27+O28 -> 10968274 | O28: =(0.25*$N$3*M27)-K28 -> 47080.15
A29: 42503 | B29: 361411.26 | D29: =+D28+F29 -> 12007447 | F29: =(0.25*$E$3*D28)-B29 -> 109221.88 | J29: 42503 | K29: 361411.26 | M29: =+M28+O29 -> 11017115 | O29: =(0.25*$N$3*M28)-K29 -> 48841.115
A30: 42595 | B30: 361411.26 | D30: =+D29+F30 -> 12120989 | F30: =(0.25*$E$3*D29)-B30 -> 113542.15 | J30: 42595 | K30: 361411.26 | M30: =+M29+O30 -> 11067783 | O30: =(0.25*$N$3*M29)-K30 -> 50667.946
A31: 42687 | B31: 361411.26 | D31: =+D30+F31 -> 12239022 | F31: =(0.25*$E$3*D30)-B31 -> 118033.29 | J31: 42687 | K31: 361411.26 | M31: =+M30+O31 -> 11120346 | O31: =(0.25*$N$3*M30)-K31 -> 52563.107
F32: =SUM(F4:F31) -> 2055126 | O32: =SUM(O4:O31) -> 936450.23
