Workbook

Sheet All Securities
A1: Instrument ID | B1: Legal Entity | C1: LEID | D1: Deal | E1: Position | F1: Income Security | G1: Security ID | H1: Type | I1: CCY | J1: Face Value | K1: Commitment | L1: Settlement Date | M1: Maturity Date | N1: IFRS 9 Class | O1: Has Children?
A2: alliance | B2: FIS Capital Partners I | C2: 7 | D2: Alliance Manufacturing | E2: FCP-I 100% holding · Alliance CN | F2: Alliance Manufacturing Convertible Note (12% / 14% PIK) | G2: SEC-ALLIANCE-2019-CN | H2: Loan | I2: GBP | J2: 25000000 | K2: 25000000 | L2: 2019-01-15 | M2: 2020-03-05 | O2: No
A3: discountBond | B3: FIS Capital Partners I | C3: 7 | D3: Copperleaf Capital | E3: FCP-I 100% holding · Copperleaf bond | F3: Copperleaf 8% Senior Notes 2030 (Discount Bond) | G3: SEC-COPPERLEAF-2030-SRNOTE | H3: Loan | I3: GBP | J3: 10000000 | K3: 10000000 | L3: 2024-06-01 | M3: 2030-06-01 | O3: No
A4: floatingLoan | B4: FIS Capital Partners II | C4: 11 | D4: Orion Industrial | E4: FCP-II £40m Position · Orion TL-B | F4: Orion Industrial Term Loan B (SOFR + 575 bps) | G4: SEC-ORION-TLB-2024 | H4: Loan | I4: GBP | J4: 40000000 | K4: 40000000 | L4: 2024-09-15 | M4: 2031-09-15 | O4: No
A5: floatingLoanFCP1 | B5: FIS Capital Partners I | C5: 7 | D5: Orion Industrial | E5: FCP-I £20m Position · Orion TL-B (Secondary) | F5: Orion Industrial Term Loan B (SOFR + 575 bps) | G5: SEC-ORION-TLB-2024 | H5: Loan | I5: GBP | J5: 20000000 | K5: 20000000 | L5: 2025-03-15 | M5: 2031-09-15 | O5: No
A6: revolver | B6: FIS Credit Opps III | C6: 22 | D6: Northwind Ventures | E6: FCO-III 100% holding · Northwind RCF | F6: Northwind Revolving Credit Facility (£50m commitment) | G6: SEC-NORTHWIND-RCF-2025 | H6: Loan | I6: GBP | J6: 15000000 | K6: 50000000 | L6: 2025-01-15 | M6: 2029-01-15 | O6: No
A7: privateCredit | B7: FIS Direct Lending Fund IV | C7: 31 | D7: Meridian Healthcare Services | E7: DL-IV 100% holding · Meridian Unitranche | F7: Meridian Unitranche Term Loan (SOFR + 600, 1% OID, 2% PIK) | G7: SEC-MERIDIAN-UNITRANCHE-2025 | H7: Loan | I7: GBP | J7: 35000000 | K7: 35000000 | L7: 2025-03-15 | M7: 2031-03-15 | O7: No
A8: libra2 | B8: NWF Sustainable Infrastructure | C8: 42 | D8: Libra 2 | E8: NWF 100% Bilateral Position · Libra 2 | F8: HSBC Facility B4 — Libra 2 (Compounded SONIA + Ratcheted Margin) | G8: SEC-LIBRA2-HSBC-FACB4 | H8: Loan | I8: GBP | J8: 25000000 | K8: 25000000 | L8: 2024-10-08 | M8: 2031-10-10 | N8: AmortisedCost | O8: No
A9: libra3 | B9: NWF Sustainable Infrastructure | C9: 42 | D9: Libra 3 | E9: NWF 100% Bilateral Position · Libra 3 (with CFH) | F9: HSBC Facility B4 — Libra 3 (Compounded SONIA + Ratcheted Margin · CFH IRS) | G9: SEC-LIBRA3-HSBC-FACB4-CFH | H9: Loan | I9: GBP | J9: 25000000 | K9: 25000000 | L9: 2024-10-08 | M9: 2031-10-10 | N9: AmortisedCost | O9: No
A10: voltGuarantee | B10: NWF Sustainable Infrastructure | C10: 42 | D10: Volt | E10: NWF Guarantor Position · Volt covered tranche | F10: Volt Financial Guarantee on £1bn BoA Loan (£800m covered) | G10: SEC-VOLT-GP017-FINGUAR | H10: Loan | I10: GBP | J10: 1000000000 | K10: 1000000000 | L10: 2025-12-18 | M10: 2037-12-17 | N10: AmortisedCost | O10: No
A11: xyzBuyoutFund | B11: NWF Renewable Equity | C11: 51 | D11: XYZ Buyout Fund (GBP) | E11: NWFE LP Subscription · £50m commitment | F11: XYZ Buyout Fund (GBP) — Limited Partnership Interest | G11: SEC-XYZ-BUYOUT-LPINT | H11: Loan | I11: GBP | J11: 50000000 | K11: 50000000 | L11: 2026-01-15 | M11: 2038-01-15 | N11: FVTPL | O11: No
A12: abcdefSeriesC | B12: NWF Renewable Equity | C12: 51 | D12: ABCDEF Software Ltd | E12: NWFE Series C Subscription · £100m · 9.09% post-money | F12: ABCDEF Software Ltd — Series C Ordinary Shares | G12: SEC-ABCDEF-SERIES-C-ORD | H12: Loan | I12: GBP | J12: 100000000 | K12: 100000000 | L12: 2026-04-01 | M12: 2036-04-01 | N12: FVTPL | O12: No
A13: suffolkMultiTranche | B13: NWF Sustainable Infrastructure | C13: 42 | D13: Suffolk Solar Phase 2 | E13: NWF 100% Bilateral Position · Suffolk Solar | F13: Suffolk Solar Multi-Tranche Facility (£50m Fixed + £50m SONIA) | G13: SEC-SUFFOLK-SOLAR-MT | H13: Multi-Tranche | I13: GBP | J13: 100000000 | K13: 100000000 | L13: 2026-01-15 | M13: 2033-01-15 | N13: AmortisedCost | O13: Yes
A14: suffolkMultiTranche/trancheA-fixed | B14: NWF Sustainable Infrastructure | C14: 42 | D14: Suffolk Solar Phase 2 | E14: NWF 100% Bilateral Position · Suffolk Solar · trancheA-fixed | F14: Suffolk Solar Multi-Tranche Facility (£50m Fixed + £50m SONIA) — trancheA-fixed | G14: trancheA-fixed | H14: Tranche | I14: GBP | J14: 50000000 | K14: 50000000 | L14: 2026-01-15 | M14: 2033-01-15 | N14: AmortisedCost | O14: No
A15: suffolkMultiTranche/trancheB-floating | B15: NWF Sustainable Infrastructure | C15: 42 | D15: Suffolk Solar Phase 2 | E15: NWF 100% Bilateral Position · Suffolk Solar · trancheB-floating | F15: Suffolk Solar Multi-Tranche Facility (£50m Fixed + £50m SONIA) — trancheB-floating | G15: trancheB-floating | H15: Tranche | I15: GBP | J15: 50000000 | K15: 50000000 | L15: 2026-01-15 | M15: 2033-01-15 | N15: AmortisedCost | O15: No
A16: voltMultiLoan | B16: NWF Sustainable Infrastructure | C16: 42 | D16: Volt — Multi-Loan Guarantee | E16: NWF Guarantor Position · Volt multi-loan covered | F16: Volt Multi-Loan Financial Guarantee (£600m covered, 2 underlyings) | G16: SEC-VOLT-GP022-MULTILOAN | H16: Guarantee | I16: GBP | J16: 750000000 | K16: 750000000 | L16: 2026-01-15 | M16: 2036-01-15 | N16: AmortisedCost | O16: Yes
A17: voltMultiLoan/underlying1-sonia | B17: NWF Sustainable Infrastructure | C17: 42 | D17: Volt — Multi-Loan Guarantee | E17: NWF Guarantor Position · Volt multi-loan covered · underlying1-sonia | F17: Volt Multi-Loan Financial Guarantee (£600m covered, 2 underlyings) — underlying1-sonia | G17: underlying1-sonia | H17: Underlying Loan | I17: GBP | J17: 400000000 | K17: 400000000 | L17: 2026-01-15 | M17: 2036-01-15 | N17: AmortisedCost | O17: No
A18: voltMultiLoan/underlying2-fixed | B18: NWF Sustainable Infrastructure | C18: 42 | D18: Volt — Multi-Loan Guarantee | E18: NWF Guarantor Position · Volt multi-loan covered · underlying2-fixed | F18: Volt Multi-Loan Financial Guarantee (£600m covered, 2 underlyings) — underlying2-fixed | G18: underlying2-fixed | H18: Underlying Loan | I18: GBP | J18: 200000000 | K18: 200000000 | L18: 2026-01-15 | M18: 2036-01-15 | N18: AmortisedCost | O18: No

Sheet Legal Entities
A1: Legal Entity | B1: LEID | C1: Deal Count | D1: Position Count | E1: Total Commitment (GBP)
A2: FIS Capital Partners I | B2: 7 | C2: =SUMPRODUCT(('All Securities'!$B$2:$B$18=A2)*(ISNUMBER(SEARCH("/",'All Securities'!$A$2:$A$18))=FALSE())*1) -> 3 | D2: =COUNTIF('All Securities'!$B$2:$B$18,A2) -> 3 | E2: =SUMPRODUCT(('All Securities'!$B$2:$B$18=A2)*(ISNUMBER(SEARCH("/",'All Securities'!$A$2:$A$18))=FALSE())*IFERROR('All Securities'!$K$2:$K$18,0)) -> 55000000
A3: FIS Capital Partners II | B3: 11 | C3: =SUMPRODUCT(('All Securities'!$B$2:$B$18=A3)*(ISNUMBER(SEARCH("/",'All Securities'!$A$2:$A$18))=FALSE())*1) -> 1 | D3: =COUNTIF('All Securities'!$B$2:$B$18,A3) -> 1 | E3: =SUMPRODUCT(('All Securities'!$B$2:$B$18=A3)*(ISNUMBER(SEARCH("/",'All Securities'!$A$2:$A$18))=FALSE())*IFERROR('All Securities'!$K$2:$K$18,0)) -> 40000000
A4: FIS Credit Opps III | B4: 22 | C4: =SUMPRODUCT(('All Securities'!$B$2:$B$18=A4)*(ISNUMBER(SEARCH("/",'All Securities'!$A$2:$A$18))=FALSE())*1) -> 1 | D4: =COUNTIF('All Securities'!$B$2:$B$18,A4) -> 1 | E4: =SUMPRODUCT(('All Securities'!$B$2:$B$18=A4)*(ISNUMBER(SEARCH("/",'All Securities'!$A$2:$A$18))=FALSE())*IFERROR('All Securities'!$K$2:$K$18,0)) -> 50000000
A5: FIS Direct Lending Fund IV | B5: 31 | C5: =SUMPRODUCT(('All Securities'!$B$2:$B$18=A5)*(ISNUMBER(SEARCH("/",'All Securities'!$A$2:$A$18))=FALSE())*1) -> 1 | D5: =COUNTIF('All Securities'!$B$2:$B$18,A5) -> 1 | E5: =SUMPRODUCT(('All Securities'!$B$2:$B$18=A5)*(ISNUMBER(SEARCH("/",'All Securities'!$A$2:$A$18))=FALSE())*IFERROR('All Securities'!$K$2:$K$18,0)) -> 35000000
A6: NWF Renewable Equity | B6: 51 | C6: =SUMPRODUCT(('All Securities'!$B$2:$B$18=A6)*(ISNUMBER(SEARCH("/",'All Securities'!$A$2:$A$18))=FALSE())*1) -> 2 | D6: =COUNTIF('All Securities'!$B$2:$B$18,A6) -> 2 | E6: =SUMPRODUCT(('All Securities'!$B$2:$B$18=A6)*(ISNUMBER(SEARCH("/",'All Securities'!$A$2:$A$18))=FALSE())*IFERROR('All Securities'!$K$2:$K$18,0)) -> 150000000
A7: NWF Sustainable Infrastructure | B7: 42 | C7: =SUMPRODUCT(('All Securities'!$B$2:$B$18=A7)*(ISNUMBER(SEARCH("/",'All Securities'!$A$2:$A$18))=FALSE())*1) -> 5 | D7: =COUNTIF('All Securities'!$B$2:$B$18,A7) -> 9 | E7: =SUMPRODUCT(('All Securities'!$B$2:$B$18=A7)*(ISNUMBER(SEARCH("/",'All Securities'!$A$2:$A$18))=FALSE())*IFERROR('All Securities'!$K$2:$K$18,0)) -> 1900000000
A8: Total | C8: =SUM(C2:C7) -> 13 | D8: =SUM(D2:D7) -> 17 | E8: =SUM(E2:E7) -> 2230000000

Sheet Deals
A1: Deal | B1: Legal Entity | C1: LEID | D1: CCY | E1: Settlement | F1: Maturity | G1: Commitment | H1: Type | I1: IFRS 9 Class | J1: Position | K1: Income Security
A2: Alliance Manufacturing | B2: FIS Capital Partners I | C2: 7 | D2: GBP | E2: 2019-01-15 | F2: 2020-03-05 | G2: 25000000 | H2: Loan | J2: FCP-I 100% holding · Alliance CN | K2: Alliance Manufacturing Convertible Note (12% / 14% PIK)
A3: Copperleaf Capital | B3: FIS Capital Partners I | C3: 7 | D3: GBP | E3: 2024-06-01 | F3: 2030-06-01 | G3: 10000000 | H3: Loan | J3: FCP-I 100% holding · Copperleaf bond | K3: Copperleaf 8% Senior Notes 2030 (Discount Bond)
A4: Orion Industrial | B4: FIS Capital Partners II | C4: 11 | D4: GBP | E4: 2024-09-15 | F4: 2031-09-15 | G4: 40000000 | H4: Loan | J4: FCP-II £40m Position · Orion TL-B | K4: Orion Industrial Term Loan B (SOFR + 575 bps)
A5: Orion Industrial | B5: FIS Capital Partners I | C5: 7 | D5: GBP | E5: 2025-03-15 | F5: 2031-09-15 | G5: 20000000 | H5: Loan | J5: FCP-I £20m Position · Orion TL-B (Secondary) | K5: Orion Industrial Term Loan B (SOFR + 575 bps)
A6: Northwind Ventures | B6: FIS Credit Opps III | C6: 22 | D6: GBP | E6: 2025-01-15 | F6: 2029-01-15 | G6: 50000000 | H6: Loan | J6: FCO-III 100% holding · Northwind RCF | K6: Northwind Revolving Credit Facility (£50m commitment)
A7: Meridian Healthcare Services | B7: FIS Direct Lending Fund IV | C7: 31 | D7: GBP | E7: 2025-03-15 | F7: 2031-03-15 | G7: 35000000 | H7: Loan | J7: DL-IV 100% holding · Meridian Unitranche | K7: Meridian Unitranche Term Loan (SOFR + 600, 1% OID, 2% PIK)
A8: Libra 2 | B8: NWF Sustainable Infrastructure | C8: 42 | D8: GBP | E8: 2024-10-08 | F8: 2031-10-10 | G8: 25000000 | H8: Loan | I8: AmortisedCost | J8: NWF 100% Bilateral Position · Libra 2 | K8: HSBC Facility B4 — Libra 2 (Compounded SONIA + Ratcheted Margin)
A9: Libra 3 | B9: NWF Sustainable Infrastructure | C9: 42 | D9: GBP | E9: 2024-10-08 | F9: 2031-10-10 | G9: 25000000 | H9: Loan | I9: AmortisedCost | J9: NWF 100% Bilateral Position · Libra 3 (with CFH) | K9: HSBC Facility B4 — Libra 3 (Compounded SONIA + Ratcheted Margin · CFH IRS)
A10: Volt | B10: NWF Sustainable Infrastructure | C10: 42 | D10: GBP | E10: 2025-12-18 | F10: 2037-12-17 | G10: 1000000000 | H10: Loan | I10: AmortisedCost | J10: NWF Guarantor Position · Volt covered tranche | K10: Volt Financial Guarantee on £1bn BoA Loan (£800m covered)
A11: XYZ Buyout Fund (GBP) | B11: NWF Renewable Equity | C11: 51 | D11: GBP | E11: 2026-01-15 | F11: 2038-01-15 | G11: 50000000 | H11: Loan | I11: FVTPL | J11: NWFE LP Subscription · £50m commitment | K11: XYZ Buyout Fund (GBP) — Limited Partnership Interest
A12: ABCDEF Software Ltd | B12: NWF Renewable Equity | C12: 51 | D12: GBP | E12: 2026-04-01 | F12: 2036-04-01 | G12: 100000000 | H12: Loan | I12: FVTPL | J12: NWFE Series C Subscription · £100m · 9.09% post-money | K12: ABCDEF Software Ltd — Series C Ordinary Shares
A13: Suffolk Solar Phase 2 | B13: NWF Sustainable Infrastructure | C13: 42 | D13: GBP | E13: 2026-01-15 | F13: 2033-01-15 | G13: 100000000 | H13: Multi-Tranche | I13: AmortisedCost | J13: NWF 100% Bilateral Position · Suffolk Solar | K13: Suffolk Solar Multi-Tranche Facility (£50m Fixed + £50m SONIA)
A14: Volt — Multi-Loan Guarantee | B14: NWF Sustainable Infrastructure | C14: 42 | D14: GBP | E14: 2026-01-15 | F14: 2036-01-15 | G14: 750000000 | H14: Guarantee | I14: AmortisedCost | J14: NWF Guarantor Position · Volt multi-loan covered | K14: Volt Multi-Loan Financial Guarantee (£600m covered, 2 underlyings)
